Workbook

Sheet Legend
B3: ID Prefix | C3: Category
B4: SEC | C4: Security
B5: PERF | C5: Performance
B6: DB | C6: Dashboard Backend
B7: MB | C7: Mobile Backend
B8: DF | C8: Dashboard Frontend
B9: MP | C9: Mobile Passenger
B10: MD | C10: Mobile Driver
B11: SA | C11: Sharapp
B12: CR | C12: Cross Repos
B13: NTH | C13: Nice to Have

Sheet Old
A1: # | B1: Milestone | C1: Scope | D1: Description | E1: Estimation
A2: 1 | B2: Security Fixes | C2: Security | D2: Fix Backend Security Issues Move frontend/app security access to backend
A3: 2 | B3: AWS Fixes | C3: AWS | D3: Reduce AWS Spend
A4: 3 | B4: Critical performance Critical Bugs | C4: Dashboard Mobile backend Mobile Driver Sharapp | D4: Improve performance fix customer facing issues Add logging
A5: 4 | B5: High Performance High Bugs
A6: 5 | B6: Critical/High UI/UX | C6: UI/UX Visual Design | D6: Improve user experience with regards to views
A7: 6 | B7: Medium/Low Performance Medium/Low bugs
A8: 7 | B8: Medium/Low UI/UX | C8: UI/UX Visual Design | D8: Finalize UI/U improvements
A9: 8 | B9: Functionality

Sheet WP
B3: # | C3: Work Package | D3: Issue Count | E3: Duration | F3: Sub-Work Packages / Deliverables
B4: =ROW() - ROW(Table3[[#Headers],['#]]) -> 1 | C4: Critical Security & Infrastructure | D4: 25 | F4: 1.1- Fix all hardcoded credentials and clean Git history 1.2- Rotate all API keys and secrets 1.3- Configure CORS properly 1.4- Implement basic rate limiting 1.5- Perform AWS security hardening (IAM policies, security groups)
B5: =ROW() - ROW(Table3[[#Headers],['#]]) -> 2 | C5: Framework Upgrades & Core Performance | F5: 2.1- Upgrade Django framework (both backends) 2.2- Fix critical N+1 queries 2.3- Optimize database performance and indexing 2.4- Conduct database migrations 2.5- Implement pagination improvements
B6: =ROW() - ROW(Table3[[#Headers],['#]]) -> 3 | C6: Authentication & Token Management | F6: 3.1- Implement token lifecycle management (access + refresh) 3.2- Use httpOnly cookies for session security 3.3- Add CSRF protection 3.4- Integrate multi-factor authentication (MFA) 3.5- Test and validate all authentication flows
B7: =ROW() - ROW(Table3[[#Headers],['#]]) -> 4 | C7: Performance Optimization | F7: 4.1- Resolve remaining N+1 queries 4.2- Optimize aggregation pipelines 4.3- Add caching (Redis / in-memory) 4.4- Conduct load testing and profiling 4.5- Implement performance monitoring dashboards
B8: =ROW() - ROW(Table3[[#Headers],['#]]) -> 5 | C8: UI/UX & Mobile | F8: 5.1- Implement UI/UX improvements (Sharapp, dashboard, mobile apps) 5.2- Fix mobile app bugs 5.3- Ensure responsive design 5.4- Perform cross-browser and device testing
B9: =ROW() - ROW(Table3[[#Headers],['#]]) -> 6 | C9: Bugs, Code Quality & Finalizing AWS | F9: 6.1- Perform code quality review and refactoring 6.2- Fix remaining bugs 6.3- Optimize AWS resources (EC2, EBS, RDS) 6.4- Conduct final system testing and validation 6.5- Prepare documentation

Sheet Planning
A3: Sub-WP | B3: ID | C3: Issue | D3: Estimate (WD) | E3: Milestone
A4: WP1: Critical Security & Infrastructure
A5: 1.1 | B5: SEC-001 | C5: Hardcoded MongoDB Credentials
B6: SEC-004 | C6: Google Maps API Key Hardcoded
B7: SEC-005 | C7: Permissive CORS Configuration
B8: SEC-017 | C8: No Secrets Management Solution
B9: SEC-023 | C9: Weak Password Policy
B10: AWS-010 | C10: Security risk: port 22 (SSH) is open to the world on most EC2 instances.
B11: AWS-019 | C11: CloudTrail management events disabled
B12: AWS-029 | C12: Application Load Balancer Security Group Misconfiguration
A13: 1.2 | B13: SEC-002 | C13: Exposed AWS Access Keys
B14: SEC-011 | C14: Missing Security Headers
B15: SEC-012 | C15: Insufficient Input Validation
B16: SEC-014 | C16: Debug Mode Enabled
B17: SEC-015 | C17: Insufficient Logging and Monitoring
B18: SEC-016 | C18: No Web Application Firewall
B19: AWS-022 | C19: MFA and key rotation gaps in IAM users
A20: 1.3 | B20: SEC-018 | C20: No API Versioning
B21: SEC-019 | C21: No SSL Certificate Pinning
B22: SEC-020 | C22: No Root/Jailbreak Detection
B23: SEC-021 | C23: Insufficient File Upload Validation
B24: SEC-025 | C24: No Database Query Optimization
B25: SEC-026 | C25: No Content Security for Stored Files
B26: AWS-026 | C26: Application Load Balancers serving HTTP health checks
A27: 1.4 | B27: SEC-006 | C27: Ineffective Rate Limiting
B28: SEC-024 | C28: No Request Size Limits
A29: 1.5 | B29: AWS-020 | C29: External resource sharing via IAM Access Analyzer findings
B30: AWS-028 | C30: Security Groups – Unrestricted Access
A31: WP2: Framework Upgrades & Core Performance
A32: 2.1 | B32: SEC-010 | C32: Outdated Django Framework
B33: PERF-DB-002 | C33: Missing Database Connection Pooling
A34: 2.2 | B34: PERF-DB-003 | C34: N+1 Query in Account Serializer
B35: PERF-DB-010 | C35: Missing Query Optimization (only/defer)
B36: PERF-DB-011 | C36: Inefficient Nested Loops Over QuerySets
B37: PERF-MB-003 | C37: N+1 in Driver Transactions
A38: 2.4 | B38: PERF-DB-013 | C38: Missing Indexes on Frequently Queried Fields
B39: PERF-MB-002 | C39: Missing Database Indexes
A40: 2.5 | B40: PERF-DB-004 | C40: Massive Aggregation Without Pagination
B41: PERF-DB-005 | C41: Inefficient Driver Pagination
B42: PERF-MP-011 | C42: No Pagination in Trip History

Sheet Summary
B1: JTNY Security Audit - Complete Analysis
B2: Critical | C2: High | D2: Medium | E2: Low | F2: Total
B3: =COUNTIFS(Security_Analysis!A:A,"*SEC*",Security_Analysis!B:B,"CRITICAL") -> 6 | C3: =COUNTIFS(Security_Analysis!A:A,"*SEC*",Security_Analysis!B:B,"HIGH") -> 11 | D3: =COUNTIFS(Security_Analysis!A:A,"*SEC*",Security_Analysis!B:B,"MEDIUM") -> 9 | E3: =COUNTIFS(Security_Analysis!A:A,"*SEC*",Security_Analysis!B:B,"LOW") -> 0 | F3: =SUM(B3:E3) -> 26
B5: JTNY Performance Audit - Complete Analysis
B6: Repository | C6: Critical | D6: High | E6: Medium | F6: Low | G6: Total
B7: DB | C7: =COUNTIFS(Performance_Analysis!A:A,"*PERF-DB*",Performance_Analysis!B:B,"CRITICAL") -> 6 | D7: =COUNTIFS(Performance_Analysis!A:A,"*PERF-DB*",Performance_Analysis!B:B,"HIGH") -> 9 | E7: =COUNTIFS(Performance_Analysis!A:A,"*PERF-DB*",Performance_Analysis!B:B,"MEDIUM") -> 12 | F7: =COUNTIFS(Performance_Analysis!A:A,"*PERF-DB*",Performance_Analysis!B:B,"LOW") -> 4 | G7: =SUM(C7:F7) -> 31
B8: MB | C8: =COUNTIFS(Performance_Analysis!A:A,"*PERF-MB*",Performance_Analysis!B:B,"CRITICAL") -> 2 | D8: =COUNTIFS(Performance_Analysis!A:A,"*PERF-MB*",Performance_Analysis!B:B,"HIGH") -> 7 | E8: =COUNTIFS(Performance_Analysis!A:A,"*PERF-MB*",Performance_Analysis!B:B,"MEDIUM") -> 6 | F8: =COUNTIFS(Performance_Analysis!A:A,"*PERF-MB*",Performance_Analysis!B:B,"LOW") -> 0 | G8: =SUM(C8:F8) -> 15
B9: DF | C9: =COUNTIFS(Performance_Analysis!A:A,"*PERF-DF*",Performance_Analysis!B:B,"CRITICAL") -> 2 | D9: =COUNTIFS(Performance_Analysis!A:A,"*PERF-DF*",Performance_Analysis!B:B,"HIGH") -> 8 | E9: =COUNTIFS(Performance_Analysis!A:A,"*PERF-DF*",Performance_Analysis!B:B,"MEDIUM") -> 4 | F9: =COUNTIFS(Performance_Analysis!A:A,"*PERF-DF*",Performance_Analysis!B:B,"LOW") -> 1 | G9: =SUM(C9:F9) -> 15
B10: MP | C10: =COUNTIFS(Performance_Analysis!A:A,"*PERF-MP*",Performance_Analysis!B:B,"CRITICAL") -> 1 | D10: =COUNTIFS(Performance_Analysis!A:A,"*PERF-MP*",Performance_Analysis!B:B,"HIGH") -> 7 | E10: =COUNTIFS(Performance_Analysis!A:A,"*PERF-MP*",Performance_Analysis!B:B,"MEDIUM") -> 6 | F10: =COUNTIFS(Performance_Analysis!A:A,"*PERF-MP*",Performance_Analysis!B:B,"LOW") -> 0 | G10: =SUM(C10:F10) -> 14
B11: MD | C11: =COUNTIFS(Performance_Analysis!A:A,"*PERF-MD*",Performance_Analysis!B:B,"CRITICAL") -> 2 | D11: =COUNTIFS(Performance_Analysis!A:A,"*PERF-MD*",Performance_Analysis!B:B,"HIGH") -> 7 | E11: =COUNTIFS(Performance_Analysis!A:A,"*PERF-MD*",Performance_Analysis!B:B,"MEDIUM") -> 5 | F11: =COUNTIFS(Performance_Analysis!A:A,"*PERF-MD*",Performance_Analysis!B:B,"LOW") -> 1 | G11: =SUM(C11:F11) -> 15
B12: SA | C12: =COUNTIFS(Performance_Analysis!A:A,"*PERF-SA*",Performance_Analysis!B:B,"CRITICAL") -> 2 | D12: =COUNTIFS(Performance_Analysis!A:A,"*PERF-SA*",Performance_Analysis!B:B,"HIGH") -> 4 | E12: =COUNTIFS(Performance_Analysis!A:A,"*PERF-SA*",Performance_Analysis!B:B,"MEDIUM") -> 3 | F12: =COUNTIFS(Performance_Analysis!A:A,"*PERF-SA*",Performance_Analysis!B:B,"LOW") -> 3 | G12: =SUM(C12:F12) -> 12
B13: CR | C13: =COUNTIFS(Performance_Analysis!A:A,"*PERF-CR*",Performance_Analysis!B:B,"CRITICAL") -> 2 | D13: =COUNTIFS(Performance_Analysis!A:A,"*PERF-CR*",Performance_Analysis!B:B,"HIGH") -> 2 | E13: =COUNTIFS(Performance_Analysis!A:A,"*PERF-CR*",Performance_Analysis!B:B,"MEDIUM") -> 2 | F13: =COUNTIFS(Performance_Analysis!A:A,"*PERF-CR*",Performance_Analysis!B:B,"LOW") -> 1 | G13: =SUM(C13:F13) -> 7
B14: NTH | C14: =COUNTIFS(Performance_Analysis!A:A,"*PERF-NTH*",Performance_Analysis!B:B,"CRITICAL") -> 0 | D14: =COUNTIFS(Performance_Analysis!A:A,"*PERF-NTH*",Performance_Analysis!B:B,"HIGH") -> 0 | E14: =COUNTIFS(Performance_Analysis!A:A,"*PERF-NTH*",Performance_Analysis!B:B,"MEDIUM") -> 0 | F14: =COUNTIFS(Performance_Analysis!A:A,"*PERF-NTH*",Performance_Analysis!B:B,"LOW") -> 10 | G14: =SUM(C14:F14) -> 10
B15: TOTAL | C15: =SUM(C7:C14) -> 17 | D15: =SUM(D7:D14) -> 44 | E15: =SUM(E7:E14) -> 38 | F15: =SUM(F7:F14) -> 20 | G15: =SUM(C15:F15) -> 119
B17: JTNY UI/UX Audit - Complete Analysis
B18: Repository | C18: Critical | D18: High | E18: Medium | F18: Low | G18: Total
B19: SA | C19: =COUNTIFS('UI-UX_Analysis'!A:A,"*UIUX-SA*",'UI-UX_Analysis'!B:B,"CRITICAL") -> 1 | D19: =COUNTIFS('UI-UX_Analysis'!A:A,"*UIUX-SA*",'UI-UX_Analysis'!B:B,"HIGH") -> 7 | E19: =COUNTIFS('UI-UX_Analysis'!A:A,"*UIUX-SA*",'UI-UX_Analysis'!B:B,"MEDIUM") -> 9 | F19: =COUNTIFS('UI-UX_Analysis'!A:A,"*UIUX-SA*",'UI-UX_Analysis'!B:B,"LOW") -> 9 | G19: =SUM(C19:F19) -> 26
B20: MD | C20: =COUNTIFS('UI-UX_Analysis'!A:A,"*UIUX-MD*",'UI-UX_Analysis'!B:B,"CRITICAL") -> 1 | D20: =COUNTIFS('UI-UX_Analysis'!A:A,"*UIUX-MD*",'UI-UX_Analysis'!B:B,"HIGH") -> 21 | E20: =COUNTIFS('UI-UX_Analysis'!A:A,"*UIUX-MD*",'UI-UX_Analysis'!B:B,"MEDIUM") -> 11 | F20: =COUNTIFS('UI-UX_Analysis'!A:A,"*UIUX-MD*",'UI-UX_Analysis'!B:B,"LOW") -> 5 | G20: =SUM(C20:F20) -> 38
B21: MP | C21: =COUNTIFS('UI-UX_Analysis'!A:A,"*UIUX-MP*",'UI-UX_Analysis'!B:B,"CRITICAL") -> 2 | D21: =COUNTIFS('UI-UX_Analysis'!A:A,"*UIUX-MP*",'UI-UX_Analysis'!B:B,"HIGH") -> 8 | E21: =COUNTIFS('UI-UX_Analysis'!A:A,"*UIUX-MP*",'UI-UX_Analysis'!B:B,"MEDIUM") -> 8 | F21: =COUNTIFS('UI-UX_Analysis'!A:A,"*UIUX-MP*",'UI-UX_Analysis'!B:B,"LOW") -> 19 | G21: =SUM(C21:F21) -> 37
B22: DF | C22: =COUNTIFS('UI-UX_Analysis'!A:A,"*UIUX-DF*",'UI-UX_Analysis'!B:B,"CRITICAL") -> 1 | D22: =COUNTIFS('UI-UX_Analysis'!A:A,"*UIUX-DF*",'UI-UX_Analysis'!B:B,"HIGH") -> 12 | E22: =COUNTIFS('UI-UX_Analysis'!A:A,"*UIUX-DF*",'UI-UX_Analysis'!B:B,"MEDIUM") -> 20 | F22: =COUNTIFS('UI-UX_Analysis'!A:A,"*UIUX-DF*",'UI-UX_Analysis'!B:B,"LOW") -> 6 | G22: =SUM(C22:F22) -> 39
B23: DB | C23: =COUNTIFS('UI-UX_Analysis'!A:A,"*UIUX-DB*",'UI-UX_Analysis'!B:B,"CRITICAL") -> 0 | D23: =COUNTIFS('UI-UX_Analysis'!A:A,"*UIUX-DB*",'UI-UX_Analysis'!B:B,"HIGH") -> 6 | E23: =COUNTIFS('UI-UX_Analysis'!A:A,"*UIUX-DB*",'UI-UX_Analysis'!B:B,"MEDIUM") -> 14 | F23: =COUNTIFS('UI-UX_Analysis'!A:A,"*UIUX-DB*",'UI-UX_Analysis'!B:B,"LOW") -> 6 | G23: =SUM(C23:F23) -> 26
B24: MB | C24: =COUNTIFS('UI-UX_Analysis'!A:A,"*UIUX-MB*",'UI-UX_Analysis'!B:B,"CRITICAL") -> 0 | D24: =COUNTIFS('UI-UX_Analysis'!A:A,"*UIUX-MB*",'UI-UX_Analysis'!B:B,"HIGH") -> 8 | E24: =COUNTIFS('UI-UX_Analysis'!A:A,"*UIUX-MB*",'UI-UX_Analysis'!B:B,"MEDIUM") -> 14 | F24: =COUNTIFS('UI-UX_Analysis'!A:A,"*UIUX-MB*",'UI-UX_Analysis'!B:B,"LOW") -> 4 | G24: =SUM(C24:F24) -> 26
B25: Total | C25: =SUM(C19:C23) -> 5 | D25: =SUM(D19:D23) -> 54 | E25: =SUM(E19:E23) -> 62 | F25: =SUM(F19:F23) -> 45 | G25: =SUM(C25:F25) -> 166
B27: JTNY Bugs & Code Quality Audit - Complete Analysis
B28: Repository | C28: Critical | D28: High | E28: Medium | F28: Low | G28: Total
B29: SA | C29: =COUNTIFS('Bugs&CodeQuality_Analysis'!A:A,"*BUGS-SA*",'Bugs&CodeQuality_Analysis'!B:B,"CRITICAL") -> 5 | D29: =COUNTIFS('Bugs&CodeQuality_Analysis'!A:A,"*BUGS-SA*",'Bugs&CodeQuality_Analysis'!B:B,"HIGH") -> 4 | E29: =COUNTIFS('Bugs&CodeQuality_Analysis'!A:A,"*BUGS-SA*",'Bugs&CodeQuality_Analysis'!B:B,"MEDIUM") -> 5 | F29: =COUNTIFS('Bugs&CodeQuality_Analysis'!A:A,"*BUGS-SA*",'Bugs&CodeQuality_Analysis'!B:B,"LOW") -> 11 | G29: =SUM(C29:F29) -> 25
B30: MP | C30: =COUNTIFS('Bugs&CodeQuality_Analysis'!A:A,"*BUGS-MP*",'Bugs&CodeQuality_Analysis'!B:B,"CRITICAL") -> 3 | D30: =COUNTIFS('Bugs&CodeQuality_Analysis'!A:A,"*BUGS-MP*",'Bugs&CodeQuality_Analysis'!B:B,"HIGH") -> 10 | E30: =COUNTIFS('Bugs&CodeQuality_Analysis'!A:A,"*BUGS-MP*",'Bugs&CodeQuality_Analysis'!B:B,"MEDIUM") -> 13 | F30: =COUNTIFS('Bugs&CodeQuality_Analysis'!A:A,"*BUGS-MP*",'Bugs&CodeQuality_Analysis'!B:B,"LOW") -> 10 | G30: =SUM(C30:F30) -> 36
B31: MD | C31: =COUNTIFS('Bugs&CodeQuality_Analysis'!A:A,"*BUGS-MD*",'Bugs&CodeQuality_Analysis'!B:B,"CRITICAL") -> 1 | D31: =COUNTIFS('Bugs&CodeQuality_Analysis'!A:A,"*BUGS-MD*",'Bugs&CodeQuality_Analysis'!B:B,"HIGH") -> 15 | E31: =COUNTIFS('Bugs&CodeQuality_Analysis'!A:A,"*BUGS-MD*",'Bugs&CodeQuality_Analysis'!B:B,"MEDIUM") -> 4 | F31: =COUNTIFS('Bugs&CodeQuality_Analysis'!A:A,"*BUGS-MD*",'Bugs&CodeQuality_Analysis'!B:B,"LOW") -> 0 | G31: =SUM(C31:F31) -> 20
B32: DF | C32: =COUNTIFS('Bugs&CodeQuality_Analysis'!A:A,"*BUGS-DF*",'Bugs&CodeQuality_Analysis'!B:B,"CRITICAL") -> 0 | D32: =COUNTIFS('Bugs&CodeQuality_Analysis'!A:A,"*BUGS-DF*",'Bugs&CodeQuality_Analysis'!B:B,"HIGH") -> 4 | E32: =COUNTIFS('Bugs&CodeQuality_Analysis'!A:A,"*BUGS-DF*",'Bugs&CodeQuality_Analysis'!B:B,"MEDIUM") -> 14 | F32: =COUNTIFS('Bugs&CodeQuality_Analysis'!A:A,"*BUGS-DF*",'Bugs&CodeQuality_Analysis'!B:B,"LOW") -> 11 | G32: =SUM(C32:F32) -> 29
B33: DB | C33: =COUNTIFS('Bugs&CodeQuality_Analysis'!A:A,"*BUGS-DB*",'Bugs&CodeQuality_Analysis'!B:B,"CRITICAL") -> 2 | D33: =COUNTIFS('Bugs&CodeQuality_Analysis'!A:A,"*BUGS-DB*",'Bugs&CodeQuality_Analysis'!B:B,"HIGH") -> 6 | E33: =COUNTIFS('Bugs&CodeQuality_Analysis'!A:A,"*BUGS-DB*",'Bugs&CodeQuality_Analysis'!B:B,"MEDIUM") -> 5 | F33: =COUNTIFS('Bugs&CodeQuality_Analysis'!A:A,"*BUGS-DB*",'Bugs&CodeQuality_Analysis'!B:B,"LOW") -> 2 | G33: =SUM(C33:F33) -> 15
B34: MB | C34: =COUNTIFS('Bugs&CodeQuality_Analysis'!A:A,"*BUGS-MB*",'Bugs&CodeQuality_Analysis'!B:B,"CRITICAL") -> 1 | D34: =COUNTIFS('Bugs&CodeQuality_Analysis'!A:A,"*BUGS-MB*",'Bugs&CodeQuality_Analysis'!B:B,"HIGH") -> 3 | E34: =COUNTIFS('Bugs&CodeQuality_Analysis'!A:A,"*BUGS-MB*",'Bugs&CodeQuality_Analysis'!B:B,"MEDIUM") -> 4 | F34: =COUNTIFS('Bugs&CodeQuality_Analysis'!A:A,"*BUGS-MB*",'Bugs&CodeQuality_Analysis'!B:B,"LOW") -> 0 | G34: =SUM(C34:F34) -> 8
B35: Total | C35: =SUM(C29:C33) -> 11 | D35: =SUM(D29:D33) -> 39 | E35: =SUM(E29:E33) -> 41 | F35: =SUM(F29:F33) -> 34 | G35: =SUM(C35:F35) -> 125
B37: JTNY AWS Audit - Complete Analysis
C38: Critical | D38: High | E38: Medium | F38: Low | G38: Total
C39: =COUNTIFS(AWS_Audit!A:A,"*AWS*",AWS_Audit!B:B,"CRITICAL") -> 13 | D39: =COUNTIFS(AWS_Audit!A:A,"*AWS*",AWS_Audit!B:B,"HIGH") -> 10 | E39: =COUNTIFS(AWS_Audit!A:A,"*AWS*",AWS_Audit!B:B,"MEDIUM") -> 5 | F39: =COUNTIFS(AWS_Audit!A:A,"*AWS*",AWS_Audit!B:B,"LOW") -> 1 | G39: =SUM(C39:F39) -> 29
B41: Total findings | G41: =SUM(F3,G15,G25,G35,G39) -> 465

Sheet Security_Analysis
A1: SEITech | M1: JTNY | Q1: SEITech
A2: ID | B2: Severity | C2: Category | D2: Issue | E2: Location | F2: Description | G2: Impact | H2: OWASP | I2: CVE/CWE | J2: Log Date | K2: Estimate (WD) | L2: Milestone | M2: Investigation Result / Team Reply | N2: Status | O2: Responsible | P2: Date of Reply | Q2: Feedback | R2: Actions Required | S2: Date of Reply | T2: Customer Feedback
A3: SEC-001 | B3: CRITICAL | C3: Credentials | D3: Hardcoded MongoDB Credentials | E3: dashboard-backend/api/settings/dev.py:26-35; mobile-backend/api/settings/dev.py | F3: Database credentials exposed in plaintext in source code, allowing anyone with repo access to compromise the entire database | G3: Complete database compromise | H3: A07:2021 - Identification and Authentication Failures | I3: CWE-798 | J3: 45963 | K3: 3 | L3: 1 | M3: After investigation, this file (dev.py) is used only for local development with a local MongoDB instance. The staging and production servers use separate configuration files (stage.env and pro.env) with environment variables — no credentials are hardcoded there. Therefore, this finding does not pose a risk to the live environment. | N3: Not an Issue / Safe | O3: Backend Team | P3: 45964 | Q3: Still a risk. Credentials in git history are permanent. Anyone with repo access (current/former employees, contractors, stolen credentials) can extract these. If dev MongoDB is network-accessible, it's compromised. | R3: *Remove credentials from git history using BFG Repo-Cleaner *Rotate MongoDB credentials immediately (delete user 'tharwat', create new) *Migrate to environment variables in .env files *Add .env files to .gitignore *Implement pre-commit hooks to prevent future credential commits | S3: 45965 | T3: 5.11.2025, by Mahmoud Biltagy: Ammar Yasser will check if any credentials are still on repo and remove it
A4: SEC-002 | B4: CRITICAL | C4: Credentials | D4: Exposed AWS Access Keys | E4: mobile-backend/api/settings/base.py:137-140 | F4: AWS IAM credentials hardcoded, enabling unauthorized access to AWS services and potential massive billing charges | G4: AWS account compromise, financial loss | H4: A05:2021 - Security Misconfiguration | I4: CWE-798 | J4: 45963 | K4: 3 | L4: 1 | M4: After investigation, we confirm this is a valid issue. The AWS credentials exposed in the source code are used for the OTP mail service (AWS SES). These credentials should not be hardcoded and require immediate handling. | N4: Valid Issue – Needs Action | O4: Backend Team | P4: 45964 | R4: *Rotate AWS IAM credentials immediately in AWS Console *Review CloudTrail logs for unauthorized usage in past 90 days *Set up billing alerts and budget caps in AWS *Move credentials to environment variables *Implement AWS Secrets Manager for credential storage *Restrict IAM policy to minimum permissions (only SES:SendEmail) *Add IP restrictions if servers have static IPs | S4: 45965
A5: SEC-003 | B5: CRITICAL | C5: Credentials | D5: Firebase Cloud Messaging Token Exposed | E5: dashboard-backend/Modules/firebase.py:9; mobile-backend/Modules/firebase.py | F5: Server token hardcoded, allowing anyone to send unauthorized push notifications to all users for phishing/spam | G5: Phishing attacks, reputation damage | H5: A05:2021 - Security Misconfiguration | I5: CWE-798 | J5: 45963 | K5: 3 | L5: 1 | M5: After investigation, the issue is valid — the Firebase server token is hardcoded for testing push notifications. This token must be protected to prevent unauthorized use. | N5: Valid Issue – Needs Action | O5: Backend Team | P5: 45964 | R5: *Regenerate Firebase server key in Firebase Console *Move token to environment variables immediately *Review Firebase notification logs for abuse *Implement notification rate limiting (max 10 per user per hour) *Add notification logging with user ID, timestamp, and IP *Implement user notification preferences | S5: 45965
A6: SEC-004 | B6: CRITICAL | C6: Credentials | D6: Google Maps API Key Hardcoded | E6: mobile-passenger/lib/shared/constants/constants.dart; mobile-driver/lib/shared/constants/constants.dart | F6: API key easily extracted from APK, enabling quota exhaustion attacks and potentially thousands in Google Cloud charges | G6: Financial loss, service disruption | H6: A05:2021 - Security Misconfiguration | I6: CWE-798 | J6: 45963 | K6: 3 | L6: 1 | M6: After investigation, the API key is hardcoded. | N6: Valid Issue – Needs Action | O6: Mobile | P6: 45964 | R6: *Set up Google Cloud billing alerts IMMEDIATELY (critical) *Restrict all 3 API keys by application signatures (Android bundle ID, iOS bundle ID) *Set daily quota limits for each Maps API in Google Cloud Console *Enable detailed API usage monitoring *For sensitive operations, implement server-side proxy *Consider API key obfuscation in mobile apps *Monitor usage daily for 30 days after fix | S6: 45965
A7: SEC-005 | B7: CRITICAL | C7: Configuration | D7: Permissive CORS Configuration | E7: dashboard-backend/api/settings/base.py; mobile-backend/api/settings/base.py | F7: CORS_ORIGIN_ALLOW_ALL = True allows any website to make authenticated requests, enabling CSRF and data theft | G7: CSRF attacks, data theft | H7: A01:2021 - Broken Access Control | I7: CWE-942 | J7: 45963 | K7: 3 | L7: 1 | M7: The configuration was confirmed during review. CORS_ORIGIN_ALLOW_ALL = True is currently active and should be restricted to specific origins. | N7: Valid Issue – Needs Action | O7: Backend Team | P7: 45964 | R7: *Change CORS_ORIGIN_ALLOW_ALL from True to False *Set CORS_ALLOWED_ORIGINS to whitelist only production, staging, and localhost domains *Enable CORS_ALLOW_CREDENTIALS = True *Implement CSRF protection for state-changing operations *Test all frontend integrations after change *Add CORS verification to deployment checklist | S7: 45965
A8: SEC-006 | B8: CRITICAL | C8: Rate Limiting | D8: Ineffective Rate Limiting | E8: dashboard-backend/api/settings/base.py; mobile-backend/api/settings/base.py | F8: Extremely high limits (5000 req/sec) allow brute force attacks, OTP enumeration, and DoS attacks | G8: Account takeover, service disruption | H8: A04:2021 - Insecure Design | I8: CWE-307 | J8: 45963 | K8: 3 | L8: 1 | M8: After investigation, high limits (5000 req/sec) are configured in the staging environment for testing purposes. In production, current throttle limits (anon: 10/minute, user: 10/second) are active, and stricter rate-limiting configurations have been applied to ensure security. | N8: Needs Discussion | O8: Backend Team | P8: 45964 | Q8: Production limit still too high. 10 requests/second per user = 600/minute = 36,000/hour. This enables OTP brute force and abuse. Industry standard for ride-sharing apps: 10-50 requests/minute per user | R8: *Implement endpoint-specific throttling classes *Configure strict rate limits: OTP (3 per 15min), Login (5 per hour), Password reset (3 per hour), General API (100 per minute) *Add IP-based rate limiting for anonymous users *Implement progressive delays after failed attempts (exponential backoff) *Add CAPTCHA after 3 failed login attempts *Log all rate limit violations with IP and user info | S8: 45965
A9: SEC-007 | B9: HIGH | C9: Authentication | D9: Excessive Token Lifetime | E9: dashboard-backend/api/settings/base.py; mobile-backend/api/settings/base.py | F9: 7-day token validity and unlimited tokens per user extend exploitation window for stolen credentials | G9: Extended attack window | H9: A07:2021 - Identification and Authentication Failures | I9: CWE-613 | J9: 45963 | K9: 2 | L9: 1 | N9: Valid Issue – Needs Action | O9: Backend Team | P9: 45964 | R9: *Reduce access token lifetime to 15-60 minutes *Implement refresh tokens with 7-30 day lifetime *Create token refresh endpoint in backend *Store refresh tokens in database with device/IP tracking *Implement automatic token refresh in frontend before expiry *Add token revocation on password change and logout *Set TOKEN_LIMIT_PER_USER to reasonable limits (3 for passengers, 2 for drivers/admins) | S9: 45965
A10: SEC-008 | B10: HIGH | C10: Storage | D10: Authentication Tokens in localStorage | E10: dashboard-frontend/src/shared/apiCall/ApiCall.js; dashboard-frontend/src/components/Login.jsx | F10: Tokens stored in localStorage are vulnerable to XSS attacks for easy theft | G10: Token theft via XSS | H10: A03:2021 - Injection | I10: CWE-922 | J10: 45963 | K10: 2 | L10: 1 | M10: Thanks for this observation . You are right for sure. I researched the issue further and didn’t realize it could be that dangerous. It indeed exposes the app to potential XSS-based token theft. From my research, I learned that the best practice for stronger security is to use three tokens: access token, refresh token, and CSRF token to help prevent CSRF attacks and improve overall authentication safety. I really appreciate your detailed feedback and contributions. I have learnt a lot from this review sheet. Thanks and Regards . | N10: Valid Issue – Needs Action | O10: Frontend and Backend | P10: 45964 | R10: *Backend: Configure Knox to use httpOnly, secure, SameSite=Strict cookies *Backend: Store refresh tokens in separate httpOnly cookies *Backend: Implement CSRF token generation and validation *Frontend: Remove all localStorage.getItem/setItem for tokens *Frontend: Let browser handle cookies automatically *Frontend: Include CSRF token in request headers *Test authentication flow thoroughly across browsers | S10: 45965
A11: SEC-009 | B11: HIGH | C11: Authentication | D11: No Multi-Factor Authentication | E11: System-wide authentication flow | F11: Only password authentication makes accounts vulnerable to phishing, credential stuffing, and password reuse attacks | G11: Account takeover | H11: A07:2021 - Identification and Authentication Failures | I11: CWE-308 | J11: 45963 | K11: 3 | L11: 1 | M11: After investigation, MFA is not implemented in the system. | N11: Valid Issue – Needs Action | O11: Backend&mobile | P11: 45964 | R11: *Implement TOTP-based MFA using existing django-otp package *Support Google Authenticator, Authy, Microsoft Authenticator *Make MFA mandatory for: All admin accounts, Drivers with 100+ trips, Users with saved payment methods *Provide recovery codes (one-time use, printable) *Add SMS backup codes as alternative *Implement MFA reset flow with identity verification *Offer optional MFA for all other users | S11: 45965
A12: SEC-010 | B12: HIGH | C12: Dependencies | D12: Outdated Django Framework | E12: dashboard-backend/requirements.txt; mobile-backend/requirements.txt | F12: Django 4.0.3 has 15+ known CVEs including critical SQL injection (CVE-2023-31047) | G12: SQL injection, RCE | H12: A06:2021 - Vulnerable and Outdated Components | I12: CVE-2023-31047 | J12: 45963 | L12: 1 | M12: After investigation, the project uses the Djongo package for MongoDB integration, which currently supports only specific Django versions. Updating Django would break Djongo compatibility. | N12: Needs Discussion | O12: Backend Team | P12: 45964 | Q12: Running known-vulnerable Django is a compliance violation. Djongo incompatibility is not an acceptable excuse. | R12: I need more research to a better option. But for now I found 3 options: *(Django 5.0 + official backend) - IF all dependencies support Django 5.0 *Second Choice: (PostgreSQL) - Best long-term if Option 1 not viable *Third Choice: (PyMongo + Custom) - If must stay on MongoDB but can't do Option 1 | S12: 45965 | T12: 5.11.2025, by Mahmoud Biltagy: It will need a lot of effort, Jtny team will still research migration strategy to not break the system
A13: SEC-011 | B13: HIGH | C13: Headers | D13: Missing Security Headers | E13: dashboard-backend/api/settings/base.py; mobile-backend/api/settings/base.py | F13: No CSP, HSTS, X-Content-Type-Options, etc., leaving app vulnerable to XSS, MITM, and clickjacking | G13: XSS, clickjacking, MITM | H13: A05:2021 - Security Misconfiguration | I13: CWE-693 | J13: 45963 | K13: 3 | L13: 1 | M13: After investigation, several key security headers are missing (CSP, HSTS, X-Content-Type-Options). | N13: Valid Issue – Needs Action | O13: Backend Team | P13: 45964 | R13: *Install django-csp package *Add SecurityHeadersMiddleware to MIDDLEWARE *Configure headers: X-Content-Type-Options: nosniff, X-Frame-Options: DENY, Strict-Transport-Security (HSTS), Content-Security-Policy (CSP), X-XSS-Protection *Add SECURE_SSL_REDIRECT = True for production *Test headers using securityheaders.com *Run Django deployment check | S13: 45965
A14: SEC-012 | B14: HIGH | C14: Input Validation | D14: Insufficient Input Validation | E14: dashboard-backend/Transaction/models.py; dashboard-backend/Trip/serializers.py; mobile-backend/Account/serializers.py | F14: No validation/sanitization enables NoSQL injection, XSS, and data corruption | G14: Data injection attacks | H14: A03:2021 - Injection | I14: CWE-20 | J14: 45963 | K14: 3 | L14: 1 | N14: Needs Discussion | O14: gray | P14: 45964 | Q14: I believe it can be assigned to Backend Team. input validation is mandatory. | R14: *Audit all Django REST Framework serializers for validation *Implement field validators for all user inputs *Add input sanitization using bleach library for HTML/text fields *Implement MongoDB query parameter validation (prevent $where, $regex abuse) *Add string length limits on all CharField/TextField *Whitelist allowed characters for critical fields (usernames, IDs, phones) *Use Django's validators.RegexValidator for pattern matching | S14: 45965
A15: SEC-013 | B15: HIGH | C15: Authentication | D15: Excessive OTP Validity Period | E15: dashboard-backend/Account/models.py; mobile-backend/Account/models.py | F15: 7-minute OTP validity (line 1116) provides extended window for brute force and social engineering attacks | G15: OTP bypass attacks | H15: A07:2021 - Identification and Authentication Failures | I15: CWE-294 | J15: 45963 | K15: 2 | L15: 1 | N15: Needs Discussion | O15: gray | P15: 45964 | Q15: 7 minutes might be acceptable for UX, but needs validation. I believe it can be assigned to the Backend Team. | R15: *Review OTP expiry configuration in Account models *Consider reducing from 7 minutes to 5 minutes (industry standard for SMS) *CRITICAL: Implement OTP attempt limiting (maximum 3-5 attempts) *Add rate limiting on OTP generation (max 3 OTPs per 15 minutes per phone) *Implement progressive delays after failed OTP attempts *Add OTP failure logging and monitoring *Conduct UX testing to ensure 5 minutes is sufficient | S15: 45965
A16: SEC-014 | B16: HIGH | C16: Configuration | D16: Debug Mode Enabled | E16: dashboard-backend/api/settings/dev.py; mobile-backend/api/settings/dev.py | F16: DEBUG = True exposes stack traces, credentials, file paths, and system architecture in error messages | G16: Information disclosure | H16: A05:2021 - Security Misconfiguration | I16: CWE-489 | J16: 45963 | K16: 1 | L16: 1 | M16: After investigation, DEBUG = True is used only in the development configuration (dev.py) for testing endpoints locally. The production server is configured with DEBUG = False and managed through the pro.env file. Therefore, this configuration does not affect the live environment. | N16: Not an Issue / Safe | O16: Backend Team | P16: 45964 | Q16: Agree, not an issue if production is secure and properly configured. | S16: 45965
A17: SEC-015 | B17: HIGH | C17: Monitoring | D17: Insufficient Logging and Monitoring | E17: System-wide; dashboard-backend/api/settings/base.py | F17: Minimal logging prevents detection of breaches, attacks, and unauthorized access; violates GDPR/PCI-DSS | G17: Undetected breaches | H17: A09:2021 - Security Logging and Monitoring Failures | I17: CWE-778 | J17: 45963 | K17: 3 | L17: 1 | M17: After investigation, current logging is minimal and defaults to Django console. Recommended to implement structured logging for authentication events, API requests, and admin actions. | N17: Needs Discussion | O17: Backend Team | P17: 45964 | Q17: Logging is a compliance requirement. | R17: *Implement structured JSON logging using Python logging library *Log all authentication events: login success/failure, logout, password changes, MFA events *Log authorization failures (403 errors) *Log admin panel actions (user edits, role changes, permission grants) *Set up log aggregation (ELK Stack, CloudWatch Logs, or Datadog) *Configure alerts for suspicious patterns: multiple failed logins, unusual API access, admin actions outside business hours *Ensure logs include: timestamp, user ID, IP address, action, outcome *Set log retention policy (90 days minimum for compliance) | S17: 45965
A18: SEC-016 | B18: HIGH | C18: Infrastructure | D18: No Web Application Firewall | E18: Infrastructure level | F18: Direct API exposure with no DDoS protection, bot detection, or traffic filtering at edge | G18: DDoS, automated attacks | H18: A05:2021 - Security Misconfiguration | I18: CWE-693 | J18: 45963 | K18: 3 | L18: 1 | N18: Valid Issue – Needs Action | O18: security | P18: 45964 | R18: *Deploy Cloudflare Free tier IMMEDIATELY (takes 15-30 minutes, zero cost) *Point domain DNS to Cloudflare nameservers *Enable WAF rules and DDoS protection (automatic) *Configure SSL/TLS (Full or Strict mode) *Add basic rate limiting rules in Cloudflare *Enable bot fight mode *Set up alerts for traffic anomalies *Review analytics for attack patterns | S18: 45965
A19: SEC-017 | B19: HIGH | C19: Secrets Management | D19: No Secrets Management Solution | E19: System-wide deployment | F19: Secrets in plaintext .env files and environment variables with no rotation, encryption, or audit trail | G19: Credential exposure | H19: A05:2021 - Security Misconfiguration | I19: CWE-798 | J19: 45963 | K19: 2 | L19: 1 | O19: gray | P19: 45964 | Q19: Can be assigned to DevOps Team. | R19: *Quick win: Implement django-environ for .env file management *Ensure all .env files are in .gitignore *Choose secrets management solution: AWS Secrets Manager ($0.40/secret/month) OR HashiCorp Vault (free, self-hosted) *Migrate all credentials to secrets manager: MongoDB, AWS, Firebase, Google Maps, OAuth secrets, SMS credentials *Implement automatic secret rotation for databases *Add secrets access audit logging *Document secret rotation procedures | S19: 45965
A20: SEC-018 | B20: MEDIUM | C20: API Design | D20: No API Versioning | E20: System-wide API endpoints | F20: Breaking changes affect all clients simultaneously; no gradual migration path | G20: Service disruption | H20: A04:2021 - Insecure Design | I20: CWE-656 | J20: 45963 | K20: 1 | L20: 1 | N20: Not an Issue | O20: Backend Team | P20: 45964 | Q20: Low priority for security. This is an operational/DevOps concern, not a security vulnerability. API versioning is good practice but not urgent for security. | R20: *Not a security priority *Consider implementing when planning breaking API changes *Options: URL-based versioning (/api/v1/), Header-based versioning | S20: 45965
A21: SEC-019 | B21: MEDIUM | C21: Mobile Security | D21: No SSL Certificate Pinning | E21: mobile-passenger/lib/services/api_service.dart; mobile-driver/lib/services/api_service.dart | F21: Mobile apps vulnerable to MITM attacks on compromised networks | G21: MITM attacks | H21: A02:2021 - Cryptographic Failures | I21: CWE-295 | J21: 45963 | K21: 2 | L21: 1 | M21: After investigation, SSL certificate pinning is not implemented. | N21: Valid Issue – Needs Action | O21: Mobile | P21: 45964 | R21: *Research Flutter certificate pinning packages (dio with pinning, flutter_ssl_pinning) *Implement dual pinning: Pin primary certificate AND backup certificate *Extract SSL certificate from production server *Implement pinning in HTTP client initialization *Test with mitmproxy to verify MITM protection *CRITICAL: Implement certificate update mechanism (backend endpoint OR app update) *Plan for certificate expiry (certificates typically 1-2 years) *Document pin update procedures *Priority higher for driver app (location/financial data) | S21: 45965
A22: SEC-020 | B22: MEDIUM | C22: Mobile Security | D22: No Root/Jailbreak Detection | E22: Mobile Passenger App; Mobile Driver App | F22: Apps run on compromised devices, enabling keylogging, memory dumping, and code injection | G22: App tampering | H22: M8 - Code Tampering | I22: CWE-919 | J22: 45963 | K22: 3 | L22: 1 | M22: After investigation, apps currently lack root/jailbreak detection. | N22: Valid Issue – Needs Action | O22: Mobile | P22: 45964 | R22: *Research Flutter packages: flutter_jailbreak_detection or trust_fall (newer, better maintained) *Implement detection on app startup and periodically during use *Decision needed: Driver app - BLOCK on rooted devices (RECOMMENDED due to GPS spoofing risk), Passenger app - WARN user but allow *Implement SafetyNet Attestation API for Android *Implement DeviceCheck for iOS *Add graceful error messages for users *Log all jailbreak detection events | S22: 45965
A23: SEC-021 | B23: MEDIUM | C23: File Upload | D23: Insufficient File Upload Validation | E23: User profile uploads; driver documents | F23: No file type/size validation enables malicious file upload, storage exhaustion, and XSS via SVG | G23: XSS, storage exhaustion | H23: A03:2021 - Injection | I23: CWE-434 | J23: 45963 | K23: 2 | L23: 1 | M23: After investigation, file uploads do not enforce allowed types or size limits. Recommended to validate file type (e.g., images only), enforce max file size | N23: Valid Issue – Needs Action | O23: backend&front&mobile | P23: 45964 | R23: *Backend: Whitelist MIME types (image/jpeg, image/png for photos; add application/pdf for documents) *Backend: Validate magic bytes, NOT just file extension *Backend: Set max file sizes (5MB for profile photos, 10MB for documents) *Backend: Sanitize filenames (remove special characters, prevent path traversal) *Frontend: Client-side file type checking before upload (UX improvement) *Frontend: Show file size before upload *Storage: Store uploads OUTSIDE web root, generate random filenames, serve via signed URLs with expiration *Optional but recommended: Scan uploaded files with ClamAV for malware *Implement file upload rate limiting *Log all file uploads with user ID | S23: 45965
A24: SEC-022 | B24: MEDIUM | C24: Session Management | D24: Unlimited Concurrent Sessions | E24: dashboard-backend/api/settings/base.py; mobile-backend/api/settings/base.py | F24: TOKEN_LIMIT_PER_USER: None enables account sharing and makes token theft undetectable | G24: Account sharing | H24: A07:2021 - Identification and Authentication Failures | I24: CWE-384 | J24: 45963 | K24: 2 | L24: 1 | M24: After investigation, TOKEN_LIMIT_PER_USER is set to None allowing unlimited concurrent sessions. | N24: Valid Issue – Needs Action | O24: Backend Team | P24: 45964 | R24: *Set TOKEN_LIMIT_PER_USER to reasonable limits: Passengers (3 devices), Drivers (2 devices), Admins (2 devices) *Implement "Active Sessions" management view in user settings *Show session details: device info, last IP, last activity time, geolocation (optional) *Allow users to revoke sessions remotely *Send email notification when new device logs in *Track tokens in database with metadata: device_info, ip_address, created_at, last_activity *Auto-revoke oldest session when limit exceeded *Update Knox configuration for token tracking | S24: 45965
A25: SEC-023 | B25: MEDIUM | C25: Password Policy | D25: Weak Password Policy | E25: dashboard-backend/api/settings/base.py | F25: Default 8-char minimum with no complexity requirements allows weak passwords like 'password123' | G25: Weak passwords | H25: A07:2021 - Identification and Authentication Failures | I25: CWE-521 | J25: 45963 | K25: 1 | L25: 1 | M25: After investigation, the current password validators enforce only minimum length. Recommended to enforce complexity rules (uppercase, lowercase, number, symbol) and optionally integrate password blacklist. | N25: Valid Issue – Needs Action | O25: Backend&mobile | P25: 45964 | R25: *Keep existing 4 Django validators (they are good baseline) *Increase MinimumLengthValidator to 10-12 characters minimum *Configure CommonPasswordValidator with larger blacklist *Consider adding explicit complexity requirements OR use strength score *Implement password strength meter in frontend (zxcvbn.js library) *Optional: Check against Have I Been Pwned API for compromised passwords *Mobile apps: Implement identical validation *Mobile apps: Add visual password strength indicator | S25: 45965
A26: SEC-024 | B26: MEDIUM | C26: DoS Protection | D26: No Request Size Limits | E26: Django settings; web server configuration | F26: No limits on payload size enables memory exhaustion DoS via large JSON/file uploads | G26: DoS attacks | H26: A04:2021 - Insecure Design | I26: CWE-400 | J26: 45963 | K26: 2 | L26: 1 | M26: After investigation, there is no current limit on request size, which could allow memory exhaustion attacks. | N26: Valid Issue – Needs Action | O26: Backend Team | P26: 45964 | R26: *Django settings: Add DATA_UPLOAD_MAX_MEMORY_SIZE = 5242880 (5MB for API requests) *Django settings: Add FILE_UPLOAD_MAX_MEMORY_SIZE = 10485760 (10MB for file uploads) *Web server (nginx): Add client_max_body_size 10M; in server block *Web server (Apache): Add LimitRequestBody 10485760 in VirtualHost *Consider per-endpoint customization using Django middleware *Test limits by attempting large uploads *Ensure appropriate error messages are returned *Document limits for API consumers | S26: 45965
A27: SEC-025 | B27: MEDIUM | C27: Performance | D27: No Database Query Optimization | E27: Various views and serializers | F27: N+1 query problems cause database overload and enable DoS via slow queries | G27: Performance degradation | H27: A04:2021 - Insecure Design | I27: CWE-400 | J27: 45963 | K27: 2 | L27: 1 | M27: After investigation, several views and serializers exhibit N+1 query patterns, which could impact performance under high load. | N27: Needs Discussion | O27: Backend Team | P27: 45964 | Q27: This is a performance issue. N+1 queries impact scalability but are not a direct security vulnerability. | S27: 45965
A28: SEC-026 | B28: MEDIUM | C28: File Access | D28: No Content Security for Stored Files | E28: User-uploaded files; media storage | F28: Predictable URLs and no access control enable unauthorized document access and enumeration | G28: Data exposure | H28: A01:2021 - Broken Access Control | I28: CWE-639 | J28: 45963 | K28: 2 | L28: 1 | M28: After investigation, user-uploaded files are accessible via predictable URLs without access control. | N28: Needs Discussion | O28: Backend Team | P28: 45964 | Q28: Depends on file types. Security requirements differ by file type. Public files (profile pictures) don't need access control. Private files (driver licenses) absolutely do. We need to classify your files and design appropriate security for each category. | R28: *Classify all file types: PUBLIC (profile pictures, car photos) vs PRIVATE (driver licenses, insurance, tax docs) *For PUBLIC files: Current setup acceptable, consider CDN for performance *For PRIVATE files (CRITICAL): Store outside MEDIA_ROOT or use private S3 bucket, Create secure file serving view with permission checks, Generate signed URLs with short expiration (1-5 minutes), *Implement file access logging *Verify authorization: Drivers can only access their own documents, Admins can access all *Log all file access attempts: user_id, file_id, timestamp, IP, outcome *Consider watermarking sensitive documents *Consider document encryption at rest for highly sensitive files | S28: 45965

Sheet Performance_Summary
A1: JTNY Performance Audit - Complete Analysis | H1: Estimated Performance Improvements
A2: Repository | B2: Critical | C2: High | D2: Medium | E2: Low | F2: Total | H2: Optimization | I2: Expected Improvement | J2: User Experience Impact
A3: DB | B3: =COUNTIFS(Performance_Analysis!A:A,"*PERF-DB*",Performance_Analysis!B:B,"CRITICAL") -> 6 | C3: =COUNTIFS(Performance_Analysis!A:A,"*PERF-DB*",Performance_Analysis!B:B,"HIGH") -> 9 | D3: =COUNTIFS(Performance_Analysis!A:A,"*PERF-DB*",Performance_Analysis!B:B,"MEDIUM") -> 12 | E3: =COUNTIFS(Performance_Analysis!A:A,"*PERF-DB*",Performance_Analysis!B:B,"LOW") -> 4 | F3: =SUM(B3:E3) -> 31 | H3: Mobile App Startup | I3: 400-1200ms → 100-300ms (70-92% faster) | J3: App opens in under 1s
A4: MB | B4: =COUNTIFS(Performance_Analysis!A:A,"*PERF-MB*",Performance_Analysis!B:B,"CRITICAL") -> 2 | C4: =COUNTIFS(Performance_Analysis!A:A,"*PERF-MB*",Performance_Analysis!B:B,"HIGH") -> 7 | D4: =COUNTIFS(Performance_Analysis!A:A,"*PERF-MB*",Performance_Analysis!B:B,"MEDIUM") -> 6 | E4: =COUNTIFS(Performance_Analysis!A:A,"*PERF-MB*",Performance_Analysis!B:B,"LOW") -> 0 | F4: =SUM(B4:E4) -> 15 | H4: Database Query Optimization | I4: 70-85% faster queries | J4: Page loads under 2s
A5: DF | B5: =COUNTIFS(Performance_Analysis!A:A,"*PERF-DF*",Performance_Analysis!B:B,"CRITICAL") -> 2 | C5: =COUNTIFS(Performance_Analysis!A:A,"*PERF-DF*",Performance_Analysis!B:B,"HIGH") -> 8 | D5: =COUNTIFS(Performance_Analysis!A:A,"*PERF-DF*",Performance_Analysis!B:B,"MEDIUM") -> 4 | E5: =COUNTIFS(Performance_Analysis!A:A,"*PERF-DF*",Performance_Analysis!B:B,"LOW") -> 1 | F5: =SUM(B5:E5) -> 15 | H5: HTTP Client Configuration | I5: 100-300ms → 10-30ms per request (70-90% faster) | J5: Instant API responses
A6: MP | B6: =COUNTIFS(Performance_Analysis!A:A,"*PERF-MP*",Performance_Analysis!B:B,"CRITICAL") -> 1 | C6: =COUNTIFS(Performance_Analysis!A:A,"*PERF-MP*",Performance_Analysis!B:B,"HIGH") -> 7 | D6: =COUNTIFS(Performance_Analysis!A:A,"*PERF-MP*",Performance_Analysis!B:B,"MEDIUM") -> 6 | E6: =COUNTIFS(Performance_Analysis!A:A,"*PERF-MP*",Performance_Analysis!B:B,"LOW") -> 0 | F6: =SUM(B6:E6) -> 14 | H6: Location Tracking (Driver App) | I6: 15-30% → 3-5% battery drain (80-90% reduction) | J6: All-day usage for drivers
A7: MD | B7: =COUNTIFS(Performance_Analysis!A:A,"*PERF-MD*",Performance_Analysis!B:B,"CRITICAL") -> 2 | C7: =COUNTIFS(Performance_Analysis!A:A,"*PERF-MD*",Performance_Analysis!B:B,"HIGH") -> 7 | D7: =COUNTIFS(Performance_Analysis!A:A,"*PERF-MD*",Performance_Analysis!B:B,"MEDIUM") -> 5 | E7: =COUNTIFS(Performance_Analysis!A:A,"*PERF-MD*",Performance_Analysis!B:B,"LOW") -> 1 | F7: =SUM(B7:E7) -> 15 | H7: Provider Selective Rebuilds | I7: 100-500ms → 10-30ms updates (80-95% faster) | J7: Smooth 60 FPS animations
A8: SA | B8: =COUNTIFS(Performance_Analysis!A:A,"*PERF-SA*",Performance_Analysis!B:B,"CRITICAL") -> 2 | C8: =COUNTIFS(Performance_Analysis!A:A,"*PERF-SA*",Performance_Analysis!B:B,"HIGH") -> 4 | D8: =COUNTIFS(Performance_Analysis!A:A,"*PERF-SA*",Performance_Analysis!B:B,"MEDIUM") -> 3 | E8: =COUNTIFS(Performance_Analysis!A:A,"*PERF-SA*",Performance_Analysis!B:B,"LOW") -> 3 | F8: =SUM(B8:E8) -> 12 | H8: Trip History Pagination | I8: 2-5s → 200-500ms load (75-90% faster) | J8: Instant scrolling, no crashes
A9: CR | B9: =COUNTIFS(Performance_Analysis!A:A,"*PERF-CR*",Performance_Analysis!B:B,"CRITICAL") -> 2 | C9: =COUNTIFS(Performance_Analysis!A:A,"*PERF-CR*",Performance_Analysis!B:B,"HIGH") -> 2 | D9: =COUNTIFS(Performance_Analysis!A:A,"*PERF-CR*",Performance_Analysis!B:B,"MEDIUM") -> 2 | E9: =COUNTIFS(Performance_Analysis!A:A,"*PERF-CR*",Performance_Analysis!B:B,"LOW") -> 1 | F9: =SUM(B9:E9) -> 7 | H9: Firestore Persistence Disabled | I9: 200-1000ms → 50-150ms first query (70-85% faster) | J9: Fresh data instantly
A10: NTH | B10: =COUNTIFS(Performance_Analysis!A:A,"*PERF-NTH*",Performance_Analysis!B:B,"CRITICAL") -> 0 | C10: =COUNTIFS(Performance_Analysis!A:A,"*PERF-NTH*",Performance_Analysis!B:B,"HIGH") -> 0 | D10: =COUNTIFS(Performance_Analysis!A:A,"*PERF-NTH*",Performance_Analysis!B:B,"MEDIUM") -> 0 | E10: =COUNTIFS(Performance_Analysis!A:A,"*PERF-NTH*",Performance_Analysis!B:B,"LOW") -> 10 | F10: =SUM(B10:E10) -> 10 | H10: Request Debouncing | I10: 70-90% reduction in API calls | J10: No lag, reduced server load
A11: TOTAL | B11: =SUM(B3:B10) -> 17 | C11: =SUM(C3:C10) -> 44 | D11: =SUM(D3:D10) -> 38 | E11: =SUM(E3:E10) -> 20 | F11: =SUM(B11:E11) -> 119 | H11: Bundle Size Optimization | I11: 50% smaller JavaScript bundles | J11: 3s faster initial page load
H12: Image Optimization | I12: 60-80% smaller images | J12: Faster page rendering
H13: Real-time Connection Pool | I13: 40-60% reduction in connections | J13: Reduced infrastructure costs
H14: Lazy Loading Maps | I14: 300-800ms → 0ms at startup (100% eliminated) | J14: Instant app launch
H15: HTTP/2 Implementation | I15: 10-20% faster initial load | J15: Reduced latency globally
H16: CDN for Static Assets | I16: 200-500ms faster globally | J16: Better international UX
H17: Database Read Replicas | I17: 40-60% improvement in reads | J17: Faster analytics & reports
H18: APM Tool Integration | I18: Real-time monitoring | J18: Proactive issue resolution
H19: Load Testing Pipeline | I19: Prevents production crashes | J19: Stable during viral growth
H20: Performance Budgets | I20: Prevents regressions | J20: Consistent fast experience
H21: Chat HTML Rendering | I21: 30-45 FPS → 60 FPS scrolling (30-100% improvement) | J21: Smooth chat scrolling
H22: Memory Leak Fixes | I22: 80% reduction in crashes | J22: Stable long sessions

Sheet Performance_Analysis
A1: SEITech | M1: JTNY | Q1: SEITech
A2: ID | B2: Severity | C2: Category | D2: Issue | E2: Location | F2: Description | G2: Impact | H2: Actions Required | I2: Standards/Guidelines Followed | J2: Log Date | K2: Estimation (WD) | L2: Milestone | M2: Investigation Result / Team Reply | N2: Status | O2: Responsible | P2: Date of Reply | Q2: Feedback | R2: Date of Reply | S2: Customer Feedback
A3: PERF-DB-001 | B3: MEDIUM | C3: Database | D3: No Database Query Optimization | E3: Various views and serializers | F3: N+1 query problems cause database overload and enable DoS via slow queries | G3: *Performance degradation under load *Multiple queries where one would suffice *Database becomes bottleneck *Poor scalability | H3: *Rewrite ORM usage to leverage select_related/prefetch_related and collapse query counts. *Add a regression test that asserts query count for the affected endpoint. *Profile the affected queries with the database profiler to capture baseline timings. *Audit indexes and execution plans, adding or adjusting indexes to support the hot path. *Enable slow-query logging and surface metrics in the APM dashboard. | I3: OWASP API Security Top 10 (API4:2023 - Unrestricted Resource Consumption); CWE-1073; Performance Best Practices | J3: 45966 | K3: 2 | L3: 6 | M3: After investigation, several views and serializers exhibit N+1 query patterns, which could impact performance under high load. | N3: Needs Discussion | O3: Backend Team | P3: 45964 | Q3: This is both a performance and security issue. N+1 queries don't just slow down your application—they create a DoS vulnerability. An attacker can repeatedly call endpoints with N+1 problems to exhaust database connections. | R3: 45965
A4: PERF-DB-002 | B4: CRITICAL | C4: Database | D4: Missing Database Connection Pooling | E4: api/settings/prod.py:27-36 | F4: No connection pooling configured for MongoDB/Djongo. Missing maxPoolSize, minPoolSize configuration. | G4: *Each request creates new connections *Connection exhaustion under load *500-1000ms latency per request *Database becomes overwhelmed with connection overhead | H4: *Configure database connection pooling values (min/max pool size, timeouts) in production settings. *Validate pooled connection reuse under load with a staging load test. *Profile the affected queries with the database profiler to capture baseline timings. *Audit indexes and execution plans, adding or adjusting indexes to support the hot path. *Enable slow-query logging and surface metrics in the APM dashboard. | I4: OWASP API Security Top 10 (API4:2023); CWE-400; Database Performance Standards | J4: 45963 | K4: 5 | L4: 3
A5: PERF-DB-003 | B5: CRITICAL | C5: Database | D5: N+1 Query in Account Serializer | E5: Account/serializers.py:83-89 | F5: get_permissions() iterates through groups.all() then permissions.all() for each group. No prefetch_related. | G5: *User with 5 groups + 10 permissions each = 55 queries instead of 1 *Adds 200-500ms per user serialization *Authentication/authorization endpoints severely slowed *Every API call potentially affected | H5: *Rewrite ORM usage to leverage select_related/prefetch_related and collapse query counts. *Add a regression test that asserts query count for the affected endpoint. *Profile the affected queries with the database profiler to capture baseline timings. *Audit indexes and execution plans, adding or adjusting indexes to support the hot path. *Enable slow-query logging and surface metrics in the APM dashboard. | I5: ORM Performance Best Practices; CWE-1073 | J5: 45963 | K5: 4 | L5: 3
A6: PERF-DB-004 | B6: CRITICAL | C6: General | D6: Massive Aggregation Without Pagination | E6: Trip/models.py:787-1451 | F6: 1450+ line aggregation pipeline with 15+ $lookup stages. No result limiting. | G6: *Fetches thousands of trips at once *Memory issues (OOM killer can terminate process) *5-10 second response times *Server crashes under concurrent load *Database CPU at 100% | H6: *Break large aggregation pipelines into optimized stages with early filtering. *Add covering indexes for fields referenced in $match/$lookup steps. *Implement server-side pagination with deterministic ordering and limits. *Expose pagination parameters to clients and document defaults. *Use memory profiling tools to identify retained objects and fix leaks. | I6: OWASP API4:2023; CWE-770; Database Performance Standards | J6: 45963 | K6: 3 | L6: 3
A7: PERF-DB-005 | B7: CRITICAL | C7: General | D7: Inefficient Driver Pagination | E7: Driver/views.py:81-306 | F7: Multiple $lookup operations without indexed fields. Fetches all data then paginates in Python. | G7: *Loads 10,000 drivers into memory before pagination *2-5 second response time *High memory consumption *Database does all work, pagination happens in application *Scalability nightmare | H7: *Break large aggregation pipelines into optimized stages with early filtering. *Add covering indexes for fields referenced in $match/$lookup steps. *Implement server-side pagination with deterministic ordering and limits. *Expose pagination parameters to clients and document defaults. *Use memory profiling tools to identify retained objects and fix leaks. | I7: API Performance Standards; Pagination Best Practices | J7: 45963 | K7: 3 | L7: 3
A8: PERF-DB-006 | B8: CRITICAL | C8: Caching | D8: Missing Caching Layer | E8: Entire codebase - no cache configuration | F8: No Redis/Memcached configured. No caching for queries, sessions, permissions, config. | G8: *Every request hits database *100-300ms wasted per request *Database becomes bottleneck *Cannot scale horizontally *Repeated computation of same data | H8: *Select the appropriate cache backend (Redis/Memcached) and integrate with the service. *Define cache invalidation triggers tied to data mutations. *Introduce a centralized cache (Redis/Memcached) for expensive lookups with clear TTL guidance. *Design a cache invalidation strategy and attach cache busting to the relevant signals. *Add cache hit/miss metrics and alerts to detect regressions. | I8: Performance Best Practices; Caching Standards | J8: 45963 | K8: 5 | L8: 3
A9: PERF-DB-007 | B9: HIGH | C9: API | D9: Synchronous File Upload in Request | E9: Account/views.py:590-637 | F9: File uploads and Firebase operations done synchronously in request/response cycle. | G9: *User waits for file I/O and Firebase operations *500-2000ms blocking time per upload *Request threads blocked during upload *Poor scalability | H9: *Handle file uploads asynchronously and use pre-signed URLs to offload work from the API. *Scan and store uploads outside of the web tier to keep requests lightweight. *Batch Firebase calls and reuse initialized clients to reduce latency. *Monitor push notification delivery SLAs after the fix. *Remove synchronous heavy lifting from the request cycle or offload it to background workers. | I9: Asynchronous Processing Best Practices; CWE-400 | J9: 45963 | K9: 2 | L9: 4
A10: PERF-DB-008 | B10: HIGH | C10: General | D10: No Celery for Heavy Operations | E10: Multiple views | F10: SMS sending, Firebase updates, Excel generation done synchronously. | G10: *Excel generation takes 3-10 seconds blocking user *Email sending blocks requests *Push notifications delay responses *Poor user experience | H10: *Introduce a resilient task queue (Celery/RQ) for heavy background operations. *Ensure jobs are idempotent and include retry/backoff policies. *Stream large Excel exports instead of loading everything into memory. *Move export generation to a background worker and notify the user when ready. *Batch Firebase calls and reuse initialized clients to reduce latency. | I10: Background Processing Standards; Task Queue Best Practices | J10: 45963 | K10: 2 | L10: 4
A11: PERF-DB-009 | B11: HIGH | C11: Memory | D11: Excel Export Loads All Data Into Memory | E11: Driver/views.py:1243-1318 | F11: Fetches all records, loads into DataFrame, generates Excel. No streaming. | G11: *50,000 drivers = 500MB+ RAM per request *10-30 seconds generation time *Potential Out of Memory (OOM) errors *Server crashes under concurrent exports | H11: *Stream large Excel exports instead of loading everything into memory. *Move export generation to a background worker and notify the user when ready. *Use memory profiling tools to identify retained objects and fix leaks. *Add guardrails and alarms on process RSS to catch regressions. *Stream large datasets instead of materializing them in memory at once. | I11: Memory Management; CWE-400 | J11: 45963 | K11: 2 | L11: 4
A12: PERF-DB-010 | B12: HIGH | C12: Database | D12: Missing Query Optimization (only/defer) | E12: Account/views.py:478, 494-499 | F12: Queries fetch all model fields when only specific fields needed. | G12: *Fetching 20 fields instead of 5 needed *2-3x more data transfer from database *Slower serialization *Higher memory usage | H12: *Profile the affected queries with the database profiler to capture baseline timings. *Audit indexes and execution plans, adding or adjusting indexes to support the hot path. *Enable slow-query logging and surface metrics in the APM dashboard. *Capture before/after performance metrics (latency, throughput, resource usage) to validate the improvement. *Update documentation and runbooks with remediation details and rollback steps. | I12: ORM Performance Best Practices; Django Framework Guidelines | J12: 45963 | K12: 2 | L12: 4
A13: PERF-DB-011 | B13: HIGH | C13: Database | D13: Inefficient Nested Loops Over QuerySets | E13: Driver/views.py:814-832 | F13: Python loop over queryset calling function for each trip individually. | G13: *1000 trips = 1000 function calls instead of 1 aggregation *5-10 seconds vs 100ms *O(n) complexity where O(1) is possible *Database hammered with queries | H13: *Break large aggregation pipelines into optimized stages with early filtering. *Add covering indexes for fields referenced in $match/$lookup steps. *Profile the affected queries with the database profiler to capture baseline timings. *Audit indexes and execution plans, adding or adjusting indexes to support the hot path. *Enable slow-query logging and surface metrics in the APM dashboard. | I13: Algorithm Efficiency Standards; CWE-1050 | J13: 45963 | K13: 3 | L13: 4
A14: PERF-DB-012 | B14: HIGH | C14: General | D14: Complex Aggregation Pipeline | E14: Driver/models.py:555-928 | F14: 20+ stage aggregation with 13 $lookup, 8 $unwind. No verified indexes. | G14: *Each unindexed lookup is O(n*m) *1000 trips = 3-8 seconds per query *Database CPU at 100% *Concurrent queries cause timeouts | H14: *Break large aggregation pipelines into optimized stages with early filtering. *Add covering indexes for fields referenced in $match/$lookup steps. *Break the work into smaller batches or streaming chunks to avoid blocking the main thread. *Instrument the endpoint with detailed latency and throughput metrics. *Review error budgets and update runbooks with the remediation procedure. | I14: Database Performance Standards; MongoDB Best Practices | J14: 45963 | K14: 2 | L14: 4
A15: PERF-DB-013 | B15: HIGH | C15: Database | D15: Missing Indexes on Frequently Queried Fields | E15: Account/models.py:105-107 | F15: No indexes on suspended_from/to, is_deleted, role despite frequent queries. | G15: *Full table scan on 100K accounts = 1-3s instead of 10-50ms *Every user query slow *Database CPU at 100% during peak times *Query time grows linearly with data | H15: *Profile the affected queries with the database profiler to capture baseline timings. *Audit indexes and execution plans, adding or adjusting indexes to support the hot path. *Enable slow-query logging and surface metrics in the APM dashboard. *Capture before/after performance metrics (latency, throughput, resource usage) to validate the improvement. *Update documentation and runbooks with remediation details and rollback steps. | I15: Database Performance Standards; CWE-1089 | J15: 45963 | K15: 3 | L15: 4
... A50: PERF-DF-002 | B50: HIGH | C50: General | D50: Heavy Dependencies | E50: package.json | F50: moment.js (289KB) when date-fns (18KB) already present. | G50: *271KB unnecessary bundle size *Slower builds *More dependencies to maintain | H50: *Run bundle analyzer reports and remove dead code. *Implement route-level code splitting for the heaviest views. *Break the work into smaller batches or streaming chunks to avoid blocking the main thread. *Instrument the endpoint with detailed latency and throughput metrics. | I50: Dependency Management; Bundle Size | J50: 45966 | K50: 2 | L50: 4
A51: PERF-DF-003 | B51: CRITICAL | C51: General | D51: No Lazy Loading for Routes | E51: Routing configuration | F51: DataGrids may render 1000+ rows without virtual scrolling. | G51: *Initial load 3-8 seconds vs optimized 0.5-2 seconds *Users see blank screen for seconds *High bounce rate *Poor First Contentful Paint (FCP) *Massive JavaScript bundle | H51: *Break the work into smaller batches or streaming chunks to avoid blocking the main thread. *Instrument the endpoint with detailed latency and throughput metrics. *Review error budgets and update runbooks with the remediation procedure. *Capture before/after performance metrics (latency, throughput, resource usage) to validate the improvement. | I51: Code Splitting; Route-Based Splitting | J51: 45966 | K51: 4 | L51: 3 | Q51: In 2025, lazy loading is table stakes for React apps. Loading ALL routes upfront means users download megabytes of JavaScript for pages they may never visit. This is like loading every book in a library into memory when you just want to read one.
A52: PERF-DF-004 | B52: HIGH | C52: Bundle | D52: Large MUI Bundle Without Tree-Shaking | E52: package.json:11-16 | F52: Multiple @mui packages, likely importing full library. | G52: *MUI bundle size: 400-800KB *Could be optimized to: 150-300KB with proper imports *Slower initial page load *Wasted bandwidth for unused components | H52: *Run bundle analyzer reports and remove dead code. *Implement route-level code splitting for the heaviest views. *Enable aggressive tree-shaking and code splitting to shrink the bundle. *Lazy-load infrequently used modules and assets. *Run bundle analyzers in CI to prevent regressions. | I52: Bundle Size Optimization; Tree-Shaking | J52: 45966 | K52: 2 | L52: 4
A53: PERF-DF-005 | B53: CRITICAL | C53: State | D53: Excessive useState/useEffect Usage | E53: 2183 occurrences across 395 files | F53: 5.5 hooks per component average. Very high density. | G53: *100-500ms lag on state updates *Unnecessary re-renders *Complex debugging | H53: *Consolidate state mutations to reduce redundant recalculations. *Use memoization or selectors to avoid re-computing derived state. *Instrument state change frequency to validate improvements. *Capture before/after performance metrics (latency, throughput, resource usage) to validate the improvement. | I53: React Best Practices; Hook Optimization | J53: 45966 | K53: 3 | L53: 3
A54: PERF-DF-006 | B54: HIGH | C54: General | D54: Missing React.memo | E54: Component files | F54: No useMemo/memo patterns found. Components re-render on every parent update. | G54: *DataGrid re-renders: 200-800ms per update *Entire lists re-render on single item change *Poor performance with large datasets | H54: *Break the work into smaller batches or streaming chunks to avoid blocking the main thread. *Instrument the endpoint with detailed latency and throughput metrics. *Review error budgets and update runbooks with the remediation procedure. *Capture before/after performance metrics (latency, throughput, resource usage) to validate the improvement. | I54: React Performance Best Practices; Re-render Optimization | J54: 45966 | K54: 2 | L54: 4
A55: PERF-DF-007 | B55: HIGH | C55: State | D55: Context Providers Without Memoization | E55: App.jsx:45-76 | F55: Context values recreated on every render. | G55: *All consumers re-render unnecessarily *50-200ms overhead per context update | H55: *Consolidate state mutations to reduce redundant recalculations. *Use memoization or selectors to avoid re-computing derived state. *Instrument state change frequency to validate improvements. *Capture before/after performance metrics (latency, throughput, resource usage) to validate the improvement. | I55: React Performance; Context API Best Practices | J55: 45966 | K55: 2 | L55: 4
A56: PERF-DF-008 | B56: MEDIUM | C56: Database | D56: QueryClient Default Config | E56: App.jsx:18 | F56: No staleTime configuration. Default means constant refetching. | G56: *Unnecessary API calls on every navigation *100-500ms delay per navigation *Higher server load *Poor offline experience | H56: *Profile the affected queries with the database profiler to capture baseline timings. *Audit indexes and execution plans, adding or adjusting indexes to support the hot path. *Enable slow-query logging and surface metrics in the APM dashboard. *Capture before/after performance metrics (latency, throughput, resource usage) to validate the improvement. | I56: React Query Best Practices; Configuration Management | J56: 45966 | K56: 2 | L56: 6
A57: PERF-DF-009 | B57: HIGH | C57: API | D57: No Request Deduplication | E57: Multiple components | F57: Multiple components likely fetching same data. | G57: *2-5x more API requests than necessary *Race conditions *Inconsistent UI state *Higher server costs | H57: *Remove synchronous heavy lifting from the request cycle or offload it to background workers. *Set strict request timeouts and paginate or stream large payloads. *Document API performance expectations and SLAs in the service contract. *Capture before/after performance metrics (latency, throughput, resource usage) to validate the improvement. | I57: API Performance; Request Management | J57: 45966 | K57: 2 | L57: 4
A58: PERF-DF-010 | B58: MEDIUM | C58: Firebase | D58: Firebase Listeners Without Cleanup | E58: Chat components | F58: Listeners likely not unsubscribed properly. | G58: *Memory leaks *Performance degradation over time *Multiple listeners firing for same event *App crashes after extended use | H58: *Batch Firebase calls and reuse initialized clients to reduce latency. *Monitor push notification delivery SLAs after the fix. *Use memory profiling tools to identify retained objects and fix leaks. *Add guardrails and alarms on process RSS to catch regressions. *Batch outbound Firebase calls and move high-volume work to asynchronous jobs. | I58: Resource Management; CWE-404 | J58: 45966 | K58: 2 | L58: 6
A59: PERF-DF-011 | B59: HIGH | C59: General | D59: Large DataGrid Without Virtualization | E59: 20+ components | F59: *1000+ rows: 2-5s render vs <200ms virtualized *Memory issues with large datasets *Janky scrolling | G59: *1000+ rows: 2-5s render vs <200ms virtualized *Memory issues with large datasets *Janky scrolling | H59: *Break the work into smaller batches or streaming chunks to avoid blocking the main thread. *Instrument the endpoint with detailed latency and throughput metrics. *Review error budgets and update runbooks with the remediation procedure. *Capture before/after performance metrics (latency, throughput, resource usage) to validate the improvement. | I59: UI Performance; Virtualization Best Practices | J59: 45966 | K59: 3 | L59: 4
A60: PERF-DF-012 | B60: MEDIUM | C60: Assets | D60: No Image Optimization | E60: vite.config.js | F60: No image compression or optimization | G60: *Images 2-5x larger than necessary *Slower page load times *Higher bandwidth costs *Poor mobile experience | H60: *Enable gzip/brotli compression for the affected endpoints or assets. *Verify compression ratios and impact on CPU usage. *Optimize image assets with responsive sizing and next-gen formats. *Serve cached variants via CDN to minimize download time. *Compress and resize images/video assets to match target resolutions. | I60: Web Performance; Asset Optimization | J60: 45966 | K60: 2 | L60: 6
A61: PERF-DF-013 | B61: LOW | C61: General | D61: Duplicate Charting Libraries | E61: package.json:24-25 | F61: Both chart.js and chartjs packages present. | G61: *50-100KB unnecessary bundle size *Potential version conflicts *Confused dependencies | H61: *Run bundle analyzer reports and remove dead code. *Implement route-level code splitting for the heaviest views. *Break the work into smaller batches or streaming chunks to avoid blocking the main thread. *Instrument the endpoint with detailed latency and throughput metrics. | I61: Dependency Management; Bundle Optimization | J61: 45966 | K61: 1 | L61: 6
A62: PERF-DF-014 | B62: MEDIUM | C62: General | D62: High Chunk Size Warning Limit | E62: vite.config.js:44 | F62: 800KB limit too permissive. Masks bloated chunks. | G62: *Large chunks slow initial load *No warnings for oversized bundles *Poor code splitting visibility | H62: *Break the work into smaller batches or streaming chunks to avoid blocking the main thread. *Instrument the endpoint with detailed latency and throughput metrics. *Review error budgets and update runbooks with the remediation procedure. *Capture before/after performance metrics (latency, throughput, resource usage) to validate the improvement. | I62: Bundle Size Management; Build Configuration | J62: 45966 | K62: 1 | L62: 6
A63: PERF-DF-015 | B63: HIGH | C63: UI/Rendering | D63: No Build-Time Env Optimization | E63: vite.config.js:59-61 | F63: process.env empty object. Vars not replaced at build time. | G63: *Runtime lookups instead of compile-time replacement. | H63: *Virtualize long lists and defer off-screen rendering where possible. *Debounce expensive layout or state updates. *Profile paint and layout timelines with browser dev tools to verify the fix. *Capture before/after performance metrics (latency, throughput, resource usage) to validate the improvement. | I63: Build Optimization; Environment Configuration | J63: 45966 | K63: 2 | L63: 4
... A103: PERF-SA-011 | B103: LOW | C103: SEO | D103: No SSR or Progressive Enhancement | E103: Client-side only rendering | F103: Page requires JavaScript to display anything | G103: *Zero SEO value *No content for crawlers *Slow first paint *Poor accessibility | H103: *Optimize critical rendering path to improve LCP and CLS scores. *Verify core web vitals in Search Console after fixing. *Add automated Lighthouse checks to CI. *Capture before/after performance metrics (latency, throughput, resource usage) to validate the improvement. | I103: Web Performance; SEO Best Practices | J103: 45967 | K103: 1 | L103: 6
A104: PERF-SA-012 | B104: LOW | C104: Testing | D104: Zero Test Coverage | E104: No test files | F104: No unit, integration, or e2e tests | G104: High regression risk. Fear of refactoring. Quality issues | H104: *Automate load/performance tests that reproduce the regression scenario. *Integrate the test suite into CI to prevent future regressions. *Capture the success criteria and thresholds in living documentation. *Capture before/after performance metrics (latency, throughput, resource usage) to validate the improvement. | I104: Software Quality Standards; Testing Best Practices | J104: 45967 | L104: 6
A105: PERF-CR-001 | B105: CRITICAL | C105: Security | D105: No API Rate Limiting | E105: All backends | F105: APIs vulnerable to abuse | G105: *System crash under load, DDoS vulnerability *Server overload risk *Poor availability | H105: *Align the fix with security best practices while maintaining performance. *Validate the changes with both security and performance regression tests. *Document the security controls that prevent future degradation. *Capture before/after performance metrics (latency, throughput, resource usage) to validate the improvement. | I105: OWASP API4:2023; CWE-770 | J105: 45967 | K105: 4 | L105: 3
A106: PERF-CR-002 | B106: CRITICAL | C106: Cost | D106: Firebase Cost Risk | E106: All repos using Firebase | F106: No usage caps or monitoring | G106: *Unpredictable Firebase costs *Risk of bill shock *No usage alerts | H106: *Batch Firebase calls and reuse initialized clients to reduce latency. *Monitor push notification delivery SLAs after the fix. *Right-size resource usage to match demand and avoid waste. *Tag resources for cost attribution and tracking. *Set cost anomaly alerts tied to performance work. | I106: Cost Optimization; Resource Usage Monitoring | J106: 45967 | K106: 4 | L106: 3
A107: PERF-CR-003 | B107: HIGH | C107: Caching | D107: No Global Caching Strategy | E107: All repositories | F107: Every request hits database | G107: *Duplicate data in different caches *Cache inconsistency *Wasted memory | H107: *Select the appropriate cache backend (Redis/Memcached) and integrate with the service. *Define cache invalidation triggers tied to data mutations. *Introduce a centralized cache (Redis/Memcached) for expensive lookups with clear TTL guidance. *Design a cache invalidation strategy and attach cache busting to the relevant signals. *Add cache hit/miss metrics and alerts to detect regressions. | I107: Architecture Best Practices; Performance Optimization | J107: 45967 | K107: 2 | L107: 4
A108: PERF-CR-004 | B108: HIGH | C108: Testing | D108: No Load Testing | E108: All repositories | F108: Performance under load unknown | G108: *Will crash on viral growth *No capacity planning *Unknown breaking points *Production failures | H108: *Automate load/performance tests that reproduce the regression scenario. *Integrate the test suite into CI to prevent future regressions. *Capture the success criteria and thresholds in living documentation. *Capture before/after performance metrics (latency, throughput, resource usage) to validate the improvement. | I108: Performance Testing; QA Standards | J108: 45967 | K108: 2 | L108: 4
A109: PERF-CR-005 | B109: MEDIUM | C109: Monitoring | D109: No APM Tools | E109: All repositories | F109: No DataDog/New Relic | G109: *Can't identify bottlenecks in production *No production visibility *Hard to debug performance issues *No alerting on degradation *Slow incident response | H109: *Define explicit SLOs for latency, throughput, and error rate. *Expand observability coverage with traces, logs, and metrics for the component. *Set up alerting thresholds that align with customer impact. *Capture before/after performance metrics (latency, throughput, resource usage) to validate the improvement. | I109: Observability Standards; Monitoring | J109: 45967 | K109: 1 | L109: 6
A110: PERF-CR-006 | B110: MEDIUM | C110: Standards | D110: No Performance Budgets | E110: All frontends | F110: No limits on metrics | G110: *Performance degrades over time *No accountability for performance *Regressions slip through CI/CD *Slow creep of bloat *No enforcement mechanism | H110: *Update engineering guidelines to codify the performance standard. *Communicate the change in guild meetings and internal docs. *Audit similar components for compliance. *Capture before/after performance metrics (latency, throughput, resource usage) to validate the improvement. | I110: Performance Management; Budget Standards | J110: 45967 | K110: 1 | L110: 6
A111: PERF-CR-007 | B111: LOW | C111: Optimization | D111: No Compression | E111: All APIs | F111: Responses not compressed | G111: 70% larger payloads | H111: *Enable gzip/brotli compression for the affected endpoints or assets. *Verify compression ratios and impact on CPU usage. *Profile hotspots and prioritize fixes with the highest ROI. *Track KPI improvements in dashboards visible to stakeholders. *Capture lessons learned in a post-remediation note. | I111: HTTP Compression; Web Performance | J111: 45967 | K111: 1 | L111: 6
A112: PERF-NTH-001 | B112: LOW | C112: Monitoring | D112: Add Application Performance Monitoring (APM) | E112: All repositories | F112: Implement APM tools like New Relic, DataDog, or Sentry Performance for real-time performance monitoring. | G112: *Can't identify performance bottlenecks *No visibility into production issues *Reactive instead of proactive | H112: *Define explicit SLOs for latency, throughput, and error rate. *Expand observability coverage with traces, logs, and *metrics for the component. *Set up alerting thresholds that align with customer impact. *Capture before/after performance metrics (latency, throughput, resource usage) to validate the improvement. | I112: Observability Standards; Performance Monitoring | J112: 45967 | K112: 2 | L112: 6
A113: PERF-NTH-002 | B113: LOW | C113: Database | D113: Implement Database Query Logging | E113: Backend settings | F113: Enable slow query logging to identify and optimize problematic queries over time. | G113: *Can't identify slow queries *Hard to optimize without data | H113: *Reduce per-request logging noise and batch expensive log writes. *Add structured logging that can be sampled under load. *Profile the affected queries with the database profiler to capture baseline timings. *Audit indexes and execution plans, adding or adjusting indexes to support the hot path. *Enable slow-query logging and surface metrics in the APM dashboard. | I113: Observability Best Practices; Performance Monitoring Standards | J113: 45967 | K113: 2 | L113: 6
A114: PERF-NTH-003 | B114: LOW | C114: Frontend | D114: Add Web Vitals Tracking | E114: Dashboard frontend | F114: Implement Google Web Vitals (LCP, FID, CLS) tracking for real user monitoring. | G114: *Can't measure real user performance. Better understanding of real-world performance and user experience. *No baseline for improvements | H114: *Capture before/after performance metrics (latency, throughput, resource usage) to validate the improvement. | I114: Web Performance Standards; User Experience | J114: 45967 | K114: 2 | L114: 6
A115: PERF-NTH-004 | B115: LOW | C115: API | D115: Implement HTTP/2 Server Push | E115: Server configuration | F115: Enable HTTP/2 with server push for critical assets to reduce round trips. | G115: *Faster initial page loads through resource pre-fetching *Reduced round trips for critical assets *Better parallelization of resource loading | H115: *Optimize image assets with responsive sizing and next-gen formats. *Serve cached variants via CDN to minimize download time. *Remove synchronous heavy lifting from the request cycle or offload it to background workers. *Set strict request timeouts and paginate or stream large payloads. | I115: HTTP/2 Standards; Web Performance | J115: 45967 | K115: 1 | L115: 6
A116: PERF-NTH-005 | B116: LOW | C116: Mobile | D116: Implement App Startup Profiling | E116: Flutter apps | F116: Add Flutter DevTools timeline recording to identify startup bottlenecks. | G116: *Data-driven startup optimization decisions *Identify slow initialization code *Better app launch experience | H116: *Profile the flow with platform profilers (Android Studio/ Instruments). *Optimize state management to avoid redundant re-renders. *Implement offline-first caching strategies for network-heavy flows. *Capture before/after performance metrics (latency, throughput, resource usage) to validate the improvement. | I116: Mobile Performance; Startup Optimization | J116: 45967 | K116: 2 | L116: 6
... A121: PERF-NTH-010 | B121: LOW | C121: Mobile | D121: Implement Adaptive Image Loading | E121: Flutter apps | F121: Load different image resolutions based on device capabilities and network conditions. | G121: *Reduced data usage and faster loading on low-end devices. | H121: *Optimize image assets with responsive sizing and next-gen formats. *Serve cached variants via CDN to minimize download time. *Profile the flow with platform profilers (Android Studio/ Instruments). *Optimize state management to avoid redundant re-renders. *Implement offline-first caching strategies for network-heavy flows. | I121: Responsive Design; Performance Optimization | J121: 45967 | K121: 1 | L121: 6

Sheet UI-UX_Analysis
A1: SEITech | M1: JTNY | Q1: SEITech
A2: ID | B2: Severity | C2: Category | D2: Issue | E2: Location | F2: Description | G2: Impact | H2: Actions Required | I2: Standards/Guidelines Followed | J2: Log Date | K2: Estimation (WD) | L2: Milestone | M2: Investigation Result / Team Reply | N2: Status | O2: Responsible | P2: Date of Reply | Q2: Feedback | R2: Date of Reply | S2: Customer Feedback
A3: UIUX-SA-001 | B3: CRITICAL | C3: UI/Responsiveness | D3: Trip info cards overflow viewport | E3: *sharapp/src/TripInformation.tsx | F3: Information cards extend beyond screen width on devices under 375px wide | G3: Critical trip details like driver phone number cut off on iPhone SE/8 users | H3: *Apply responsive layout updates, verify on target breakpoints, and add visual regression coverage. | I3: Responsive Web Design Best Practices | J3: 45970 | L3: 5
A4: UIUX-SA-002 | B4: HIGH | C4: Bug - State Management | D4: Missing Loading States for Payment Link Creation | E4: *sharapp/src/TripSharingPage.tsx | F4: Button is disabled during payment creation but doesn't show loading indicator. Users don't know if action is processing. | G4: Major disruption for SharApp because Button is disabled during payment creation but doesn't show loading indicator. Users don't know if action is processing. As a result, screens desynchronize and user actions repeat. | H4: *Add loading spinner or text change to indicate processing state. | I4: Material Design - Progress and Loading Indicators; Nielsen Norman Visibility of System Status | J4: 45970 | L4: 5
A5: UIUX-SA-003 | B5: HIGH | C5: Bug - Performance | D5: Missing rel Attributes on External Links | E5: *sharapp\src\DownloadLinks.tsx (Lines 5-11) | F5: External links without rel="noopener noreferrer" pose security risks (tabnabbing) and performance issues. | G5: Major disruption for SharApp because External links without rel="noopener noreferrer" pose security risks (tabnabbing) and performance issues. As a result, latency spikes and resource exhaustion follow. | H5: *Add rel="noopener noreferrer" and target="_blank" to all external links. | I5: OWASP ASVS v4.0 V14.4 External Link Handling; HTML rel Attribute Best Practices | J5: 45970 | L5: 5
A6: UIUX-SA-004 | B6: HIGH | C6: UI/Layout Issue | D6: Mobile view map unusable | E6: *sharapp/src/TripSharingPage.tsx | F6: Google Map controls and trip info overlap on mobile screens making both unusable | G6: Mobile web users cannot track trips effectively, affecting 60% of sharapp traffic | H6: *Refactor the layout per the design system, ensure adaptive breakpoints, and validate with QA/Design. | I6: JTNY Admin Layout Guidelines | J6: 45970 | L6: 5
A7: UIUX-SA-005 | B7: HIGH | C7: UI/Navigation | D7: No back navigation option | E7: *sharapp/src/TripSharingPage.tsx | F7: Once trip page loads, no way to go back or exit without browser back | G7: Users get stuck viewing expired trips with no clear exit | H7: Provide clear navigation controls, persist state, and add UX/integration tests for the flow. | I7: Jakob Nielsen Navigation Heuristics | J7: 45970 | L7: 5
A8: UIUX-SA-006 | B8: HIGH | C8: Visual/Color & Theme | D8: Poor contrast on status badges | E8: *sharapp/src/TripInformation.tsx | F8: Light yellow text on white background for pending status | G8: Status information illegible, especially in bright environments | H8: Align styling with the JTNY brand palette, verify contrast ratios, and sync shared theme tokens. | I8: JTNY Brand System | J8: 45970 | L8: 5
A9: UIUX-SA-007 | B9: HIGH | C9: UI/Responsiveness | D9: Map doesn't resize dynamically | E9: *sharapp/src/TripSharingMap.tsx | F9: Google Map component has fixed height not adapting to content | G9: Map either too small or causes scroll on different devices | H9: Apply responsive layout updates, verify on target breakpoints, and add visual regression coverage. | I9: Responsive Web Design Best Practices | J9: 45970 | L9: 5
A10: UIUX-SA-008 | B10: HIGH | C10: UI/Accessibility | D10: Missing alt text for images | E10: *sharapp/src/TripInformation.tsx | F10: Driver/passenger avatars have no alt attributes | G10: Screen readers cannot describe images | H10: Apply WCAG-compliant changes (aria labels, focus order, contrast) and verify with assistive tech. | I10: WCAG 2.1 Level AA | J10: 45970 | L10: 5
A11: UIUX-SA-009 | B11: MEDIUM | C11: UI/UX - Layout & Responsiveness | D11: Poor Responsive Design for Map Height | E11: *sharapp/src/App.tsx | F11: Fixed viewport height for map may be too large on mobile devices, leaving little room for trip information. No breakpoint adjustments. | G11: Noticeable degradation for SharApp because Fixed viewport height for map may be too large on mobile devices, leaving little room for trip information. No breakpoint adjustments. As a result, critical UI hides content on key breakpoints. | H11: *Use responsive height classes (e.g., h-[40vh] sm:h-[50vh] lg:h-[60vh]). | I11: W3C Responsive Web Design Principles; CSS Flexible Box Specification | J11: 45970
A12: UIUX-SA-010 | B12: MEDIUM | C12: UI/UX - Layout & Responsiveness | D12: Inconsistent Spacing and Padding | E12: *sharapp\src\TripInformation.tsx | F12: Mixed use of padding classes (pt-4 px-2, sm:p-8, py-4 sm:py-0). Layout looks inconsistent across breakpoints. | G12: Noticeable degradation for SharApp because Mixed use of padding classes (pt-4 px-2, sm:p-8, py-4 sm:py-0). Layout looks inconsistent across breakpoints. As a result, critical UI hides content on key breakpoints. | H12: *Standardize spacing scale using consistent Tailwind spacing utilities. | I12: Material Design Layout and Spacing System; Design System Consistency Guidelines | J12: 45970
A13: UIUX-SA-011 | B13: MEDIUM | C13: UI/Accessibility | D13: No keyboard shortcuts | E13: *sharapp/src/App.tsx | F13: Cannot navigate or interact using keyboard only | G13: Completely inaccessible to users relying on keyboard navigation | H13: Apply WCAG-compliant changes (aria labels, focus order, contrast) and verify with assistive tech. | I13: WCAG 2.1 Level AA | J13: 45970 | L13: 7
A14: UIUX-SA-012 | B14: MEDIUM | C14: Visual/Styling | D14: Inconsistent component styling | E14: *sharapp/src/App.tsx | F14: Mix of Tailwind utilities and inline styles creating inconsistency | G14: Unprofessional appearance damaging brand credibility | H14: Normalize the component styling per the design system and run a UX review of the updated elements. | I14: Material Design Visual Guidelines | J14: 45970 | L14: 7
A15: UIUX-SA-013 | B15: MEDIUM | C15: UI/Layout Issue | D15: Download links overlap footer | E15: *sharapp/src/DownloadLinks.tsx | F15: App store buttons cover footer text on short viewports | G15: Contact information hidden on landscape mobile | H15: Refactor the layout per the design system, ensure adaptive breakpoints, and validate with QA/Design. | I15: JTNY Admin Layout Guidelines | J15: 45970 | L15: 7
A16: UIUX-SA-014 | B16: MEDIUM | C16: UI/Navigation | D16: No loading progress indicator | E16: *sharapp/src/TripInformation.tsx | F16: No indication of loading progress for slow connections | G16: Users abandon page thinking it's broken | H16: Provide clear navigation controls, persist state, and add UX/integration tests for the flow. | I16: Jakob Nielsen Navigation Heuristics | J16: 45970 | L16: 7
A17: UIUX-SA-015 | B17: MEDIUM | C17: Visual/Consistency | D17: Inconsistent date formats | E17: *sharapp/src/utils.ts | F17: Mix of DD/MM/YYYY and MM/DD/YYYY formats | G17: Date confusion for international users | H17: Normalize the component styling per the design system and run a UX review of the updated elements. | I17: Material Design Visual Guidelines | J17: 45970 | L17: 7
A18: UIUX-SA-016 | B18: MEDIUM | C18: UI/Responsiveness | D18: Text truncation issues | E18: *sharapp/src/TripInformation.tsx | F18: Long names and addresses cut off with ellipsis | G18: Important information hidden from users | H18: Apply responsive layout updates, verify on target breakpoints, and add visual regression coverage. | I18: Responsive Web Design Best Practices | J18: 45970 | L18: 7
A19: UIUX-SA-017 | B19: MEDIUM | C19: Visual/Color & Theme | D19: Inactive state unclear | E19: *sharapp/src/TripInformation.tsx | F19: Completed trips use same colors as active | G19: Users confused about trip status | H19: Align styling with the JTNY brand palette, verify contrast ratios, and sync shared theme tokens. | I19: JTNY Brand System | J19: 45970 | L19: 7
A20: UIUX-SA-018 | B20: LOW | C20: Bug - Error Handling | D20: Missing Favicon Fallbacks | E20: *sharapp\index.html (Line 5) | F20: Only SVG favicon provided. Older browsers may not support SVG favicons. | G20: Minor inconsistency for SharApp because Only SVG favicon provided. Older browsers may not support SVG favicons. As a result, users lose confidence. | H20: Normalize the component styling per the design system and run a UX review of the updated elements. | I20: W3C HTML Link Icon Specification; Web App Manifest Guidelines | J20: 45970
A21: UIUX-SA-019 | B21: LOW | C21: Bug - Error Handling | D21: No Language Attribute Fallback | E21: *sharapp\index.html (Line 2) | F21: Language is hardcoded as English, but app shows phone numbers and may serve international users. | G21: Minor inconsistency for SharApp because Language is hardcoded as English, but app shows phone numbers and may serve international users. As a result, users lose confidence. | H21: *Consider dynamic language switching or ensure content matches declared language. | I21: WCAG 2.1 Success Criterion 3.1.1 Language of Page | J21: 45970
A22: UIUX-SA-020 | B22: LOW | C22: Bug - Performance | D22: No Cache-Busting for Static Assets | E22: *All components referencing static assets | F22: Users may see stale images after updates due to browser caching. | G22: Minor inconsistency for SharApp because Users may see stale images after updates due to browser caching. As a result, latency spikes and resource exhaustion follow. | H22: * Vite handles this automatically in production builds, but verify configuration. | I22: MDN HTTP Caching Best Practices; Google Lighthouse Cache Busting Guidance | J22: 45970
A23: UIUX-SA-021 | B23: LOW | C23: Visual/Consistency | D23: Multiple loading states | E23: *sharapp/src/Skeleton.tsx | F23: Different loading indicators for map vs data vs payment | G23: Confusing user experience with no unified loading pattern | H23: Normalize the component styling per the design system and run a UX review of the updated elements. | I23: Material Design Visual Guidelines | J23: 45970 | L23: 7
A24: UIUX-SA-022 | B24: LOW | C24: Visual/Styling | D24: Pixelated avatar images | E24: *sharapp/src/TripInformation.tsx | F24: Low resolution profile images stretched to fit | G24: Poor visual quality | H24: Normalize the component styling per the design system and run a UX review of the updated elements. | I24: Material Design Visual Guidelines | J24: 45970 | L24: 7
A25: UIUX-SA-023 | B25: LOW | C25: UI/Layout Issue | D25: Header logo cut off | E25: *sharapp/src/Header.tsx | F25: JTNY logo cropped on narrow screens | G25: Brand identity compromised | H25: Refactor the layout per the design system, ensure adaptive breakpoints, and validate with QA/Design. | I25: JTNY Admin Layout Guidelines | J25: 45970 | L25: 7
A26: UIUX-SA-024 | B26: LOW | C26: UI/Navigation | D26: No breadcrumbs | E26: *sharapp/src/App.tsx | F26: No indication of where user is in flow | G26: Disorienting user experience | H26: Provide clear navigation controls, persist state, and add UX/integration tests for the flow. | I26: Jakob Nielsen Navigation Heuristics | J26: 45970 | L26: 7
A27: UIUX-SA-025 | B27: LOW | C27: Visual/Consistency | D27: Button sizes inconsistent | E27: *sharapp/src/Button.tsx | F27: CTA buttons have different heights | G27: Unprofessional appearance | H27: Normalize the component styling per the design system and run a UX review of the updated elements. | I27: Material Design Visual Guidelines | J27: 45970 | L27: 7
A28: UIUX-SA-026 | B28: LOW | C28: UI/Accessibility | D28: No skip navigation | E28: *sharapp/src/App.tsx | F28: No skip to content link for screen readers | G28: Slower navigation for accessibility users | H28: Provide clear navigation controls, persist state, and add UX/integration tests for the flow. | I28: WCAG 2.1 Level AA | J28: 45971 | L28: 7
A29: UIUX-MP-001 | B29: CRITICAL | C29: UI/Layout Issue | D29: Map search bar covers location pin | E29: *mobile-passenger/lib/modules/picking_map_point/screens/picking_map_point.dart | F29: Address search bar overlaps map center pin making selection difficult | G29: Users cannot accurately select pickup/dropoff locations | H29: Refactor the layout per the design system, ensure adaptive breakpoints, and validate with QA/Design. | I29: JTNY Admin Layout Guidelines | J29: 45971 | L29: 5
A30: UIUX-MP-002 | B30: CRITICAL | C30: UI/Navigation | D30: Stuck in loading screen | E30: *mobile-passenger/lib/modules/home_page/screens/home_screen.dart | F30: Infinite loading spinner if location services off | G30: App completely unusable without location | H30: Provide clear navigation controls, persist state, and add UX/integration tests for the flow. | I30: Jakob Nielsen Navigation Heuristics | J30: 45971 | L30: 5
A31: UIUX-MP-003 | B31: HIGH | C31: Bug - API Integration | D31: Hardcoded Serving Areas Instead of API Response | E31: *mobile-passenger\lib\shared\providers\user_provider.dart:73-218 | F31: The getVersion() method ignores the API response for service zones and uses hardcoded Egyptian areas instead, with a comment suggesting the data comes from the API. | G31: Service areas cannot be updated dynamically. The app will not work correctly in other regions. Updates require app redeployment. | H31: Apply responsive layout updates, verify on target breakpoints, and add visual regression coverage. | I31: API-Driven Development, Clean Architecture | J31: 45971
A32: UIUX-MP-004 | B32: HIGH | C32: Bug - Error Handling | D32: No Offline Handling or Network State Management | E32: *mobile-passenger\lib\main.dart:77-78 (ConnectivityProvider commented out) | F32: ConnectivityProvider is commented out in main.dart. No offline mode implementation. Users get generic error messages when network is unavailable. | G32: Poor user experience when network is unstable. App appears broken during connectivity issues. No cached data available offline. | H32: Provide clear navigation controls, persist state, and add UX/integration tests for the flow. | I32: Mobile App UX Best Practices, Offline-First Architecture | J32: 45971
A33: UIUX-MP-005 | B33: HIGH | C33: UI/Responsiveness | D33: Payment methods cut off on SE models | E33: *mobile-passenger/lib/modules/trip_settings/screens/trip_info.dart | F33: Payment selection buttons extend beyond screen on iPhone SE | G33: 15% of iOS users cannot select payment methods | H33: Apply WCAG-compliant changes (aria labels, focus order, contrast) and verify with assistive tech. | I33: Responsive Web Design Best Practices | J33: 45971 | L33: 5
A34: UIUX-MP-006 | B34: HIGH | C34: UI/Navigation | D34: No loading state during booking | E34: *mobile-passenger/lib/modules/home_page/widgets/single_trip_data.dart | F34: No visual feedback when booking request is processing | G34: Users tap multiple times creating duplicate requests | H34: Refactor the layout per the design system, ensure adaptive breakpoints, and validate with QA/Design. | I34: Jakob Nielsen Navigation Heuristics | J34: 45971 | L34: 5
A35: UIUX-MP-007 | B35: HIGH | C35: UI/Accessibility | D35: Color-only status indicators | E35: *mobile-passenger/lib/modules/home_page/widgets/single_trip_data.dart | F35: Trip status shown only through colors without text | G35: Colorblind users cannot determine trip status | H35: Apply WCAG-compliant changes (aria labels, focus order, contrast) and verify with assistive tech. | I35: WCAG 2.1 Level AA | J35: 45971 | L35: 5
A36: UIUX-MP-008 | B36: HIGH | C36: UI/Layout Issue | D36: Driver info card blocks map | E36: *mobile-passenger/lib/modules/home_page/widgets/single_trip_data.dart | F36: Driver details card covers 60% of map during trip | G36: Cannot see route or driver location properly | H36: Refactor the layout per the design system, ensure adaptive breakpoints, and validate with QA/Design. | I36: JTNY Admin Layout Guidelines | J36: 45971 | L36: 5
A37: UIUX-MP-009 | B37: HIGH | C37: Visual/Consistency | D37: RTL layout broken | E37: *mobile-passenger/lib/shared/utils/language_utils.dart | F37: Arabic text alignment issues throughout app | G37: Arabic version nearly unusable | H37: Refactor the layout per the design system, ensure adaptive breakpoints, and validate with QA/Design. | I37: JTNY Admin Layout Guidelines | J37: 45971 | L37: 5
A38: UIUX-MP-010 | B38: HIGH | C38: Visual/Color & Theme | D38: Insufficient contrast | E38: *mobile-passenger/lib/shared/constants/colors_constant.dart | F38: Light gray text on white background | G38: Text unreadable in bright sunlight | H38: Align styling with the JTNY brand palette, verify contrast ratios, and sync shared theme tokens. | I38: JTNY Brand System | J38: 45971 | L38: 5
A39: UIUX-MP-011 | B39: MEDIUM | C39: Bug - Performance | D39: Lack of Const Constructors Missing `const` Keywords on Immutable Widgets | E39: *Throughout application – many widgets that could be `const` are not | F39: Many stateless widgets and immutable widgets are not marked as `const`, missing significant optimization opportunities. Flutter can skip rebuilding `const` widgets entirely. | G39: Unnecessary widget rebuilds consume CPU, increase memory usage, and slow rendering performance. This may lead to poor frame rates and increased battery drain. | H39: Normalize the component styling per the design system and run a UX review of the updated elements. | I39: Flutter Performance Best Practices, Dart Const Documentation | J39: 45971
A40: UIUX-MP-012 | B40: MEDIUM | C40: Bug - API Integration | D40: Hardcoded Strings Not Using Localization | E40: *mobile-passenger\lib\modules\authentication\sign_in\screens\login.dart:360 ("─────── OR ───────"),; notification_api.dart:173 ("trip cancelled") | F40: Several UI strings are hardcoded instead of using AppLocalizations, making them not translatable. | G40: Incomplete internationalization. Mixed languages in UI for non-English users. Maintenance difficulty. | H40: *Move all hardcoded strings to localization files | I40: Flutter Internationalization Best Practices | J40: 45971
A41: UIUX-MP-013 | B41: MEDIUM | C41: Visual/Styling | D41: Misaligned car class images | E41: *mobile-passenger/lib/modules/trip_settings/screens/trip_info.dart | F41: Vehicle images not centered in selection cards | G41: Unprofessional appearance affecting brand perception | H41: Normalize the component styling per the design system and run a UX review of the updated elements. | I41: Material Design Visual Guidelines | J41: 45971 | L41: 7
A42: UIUX-MP-014 | B42: MEDIUM | C42: Visual/Consistency | D42: Three different modal styles | E42: *mobile-passenger/lib/shared/widgets/dialogs.dart | F42: Popup modals have different animations and styles | G42: Inconsistent user experience | H42: Normalize the component styling per the design system and run a UX review of the updated elements. | I42: Material Design Visual Guidelines | J42: 45971 | L42: 7
A43: UIUX-MP-015 | B43: MEDIUM | C43: UI/Responsiveness | D43: Time picker unusable in landscape | E43: *mobile-passenger/lib/modules/trip_settings/screens/trip_info.dart | F43: Schedule trip time picker cut off in landscape mode | G43: Cannot schedule trips with device rotated | H43: Apply responsive layout updates, verify on target breakpoints, and add visual regression coverage. | I43: Responsive Web Design Best Practices | J43: 45971 | L43: 7
A44: UIUX-MP-016 | B44: MEDIUM | C44: UI/Accessibility | D44: Buttons too small | E44: *mobile-passenger/lib/shared/widgets/custom_button.dart | F44: Critical buttons below 44px touch target | G44: Difficult for elderly or motor-impaired users | H44: Apply WCAG-compliant changes (aria labels, focus order, contrast) and verify with assistive tech. | I44: WCAG 2.1 Level AA | J44: 45971 | L44: 7
A45: UIUX-MP-017 | B45: MEDIUM | C45: UI/Layout Issue | D45: Overlapping price estimates | E45: *mobile-passenger/lib/modules/trip_settings/screens/trip_info.dart | F45: Price range text overlaps with car class name | G45: Cannot read pricing information | H45: Refactor the layout per the design system, ensure adaptive breakpoints, and validate with QA/Design. | I45: JTNY Admin Layout Guidelines | J45: 45971 | L45: 7
A46: UIUX-MP-018 | B46: MEDIUM | C46: UI/Navigation | D46: Deep link handling broken | E46: *mobile-passenger/lib/config/routes/app_routes.dart | F46: Share trip links don't open correct screen | G46: Cannot share trip details effectively | H46: Provide clear navigation controls, persist state, and add UX/integration tests for the flow. | I46: Jakob Nielsen Navigation Heuristics | J46: 45971 | L46: 7
A47: UIUX-MP-019 | B47: LOW | C47: Visual - Color & Theme | D47: Inconsistent Color Usage Colors Not Consistently Using Theme | E47: Throughout application – mix of `Colors.white`, hex values, and theme colors | F47: Colors are used inconsistently – sometimes from theme (`Theme.of(context).colorScheme`), sometimes hardcoded (`Colors.white`), sometimes from `ColorsConstant` class. No single source of truth. | G47: Inconsistent appearance across app. Difficulty maintaining design system. Hard to implement dark mode. Brand color updates require changes in multiple places. | H47: Align styling with the JTNY brand palette, verify contrast ratios, and sync shared theme tokens. | I47: Material Design Color System, Theme Management Best Practices | J47: 45971
A48: UIUX-MP-020 | B48: LOW | C48: UI/UX - Feedback & Status | D48: No Haptic Feedback Missing Tactile Feedback on Interactions | E48: Throughout application – buttons and interactions lack haptic feedback | F48: No haptic/vibration feedback on button presses, swipes, or important actions despite vibration package being available in dependencies. This is a modern mobile UX expectation. | G48: Less engaging tactile experience and reduced user satisfaction. Accessibility issue for users who rely on haptic feedback. The app feels less polished compared to competitors. | H48: *Add `HapticFeedback.lightImpact()` on standard button presses. | I48: Mobile UX Best Practices, iOS Human Interface Guidelines, Material Design Motion | J48: 45971
A49: UIUX-MP-021 | B49: LOW | C49: UI/UX - General Experience | D49: No Pull-to-Refresh Functionality Data Lists Cannot Be Refreshed by User | E49: Trip lists, transaction lists, address lists throughout application | F49: Trip lists, transaction lists, and other data lists don't have pull-to-refresh capability. Users have no way to manually refresh data. | G49: Users cannot easily refresh data when they know it should be updated. They must navigate away and back to refresh. This leads to poor mobile UX compared to expected behavior, and users may see stale data. | H49: *Add `RefreshIndicator` widget to all list views. | I49: Material Design Refresh Patterns, Mobile UX Conventions | J49: 45971
A50: UIUX-MP-022 | B50: LOW | C50: Bug - Build & Tooling | D50: No Dark Mode Support Only Light Theme Implemented | E50: Theme configuration in `mobile-passenger\lib\main.dart:121` | F50: Application only supports light theme. No dark mode implementation despite being a common feature in modern apps and improving accessibility. | G50: Poor user experience in low-light conditions. Increased eye strain for users in dark environments. Increased battery drain on OLED/AMOLED devices. Not following OS theme preferences. Lower user satisfaction. | H50: *Design comprehensive dark theme color scheme. | I50: Material Design Dark Theme Guidelines, Accessibility Best Practices | J50: 45971
A51: UIUX-MP-023 | B51: LOW | C51: Bug - Performance | D51: Missing Performance Monitoring No Production Performance Tracking | E51: No Firebase Performance or similar integration visible | F51: No performance monitoring or analytics to track app performance in production. Performance bottlenecks and improvements cannot be monitored. | G51: Cannot identify performance bottlenecks in production. No visibility into real user experience metrics. Cannot track performance improvements from optimizations. No alerts for performance degradation. Cannot correlate crashes with performance issues. | H51: *Integrate Firebase Performance Monitoring (Firebase already integrated). | I51: Mobile App Performance Monitoring Best Practices, Firebase Performance | J51: 45971
A52: UIUX-MP-024 | B52: LOW | C52: Bug - Security & Privacy | D52: No Onboarding Completion Tracking Onboarding State Not Properly Tracked | E52: *mobile-passenger\lib\data\local\cache_helper.dart (`onBoardingSkip` key exists) | F52: Onboarding can only be “skipped” but there is no proper completion tracking. No distinction between users who completed onboarding vs. skipped it. Users might see onboarding repeatedly. | G52: Potentially annoying user experience if onboarding shows unexpectedly. Unclear onboarding state management. Cannot track onboarding completion metrics. Users who skip might miss important information. | H52: *Add separate `onBoardingCompleted` key independent of skip. | I52: Onboarding UX Best Practices, User Analytics | J52: 45971
A53: UIUX-MP-025 | B53: LOW | C53: Visual - Color & Theme | D53: Inconsistent Color Usage | E53: Throughout application - mix of Colors.white, direct color values, and theme colors | F53: Colors are used inconsistently - sometimes from theme, sometimes hardcoded, sometimes from ColorsConstant. | G53: Inconsistent appearance, difficulty maintaining design system, hard to implement dark mode. | H53: *Consolidate all colors in theme | I53: Material Design Color System | J53: 45971
A54: UIUX-MP-026 | B54: LOW | C54: UI/UX - Feedback & Status | D54: No Haptic Feedback | E54: Throughout application - buttons and interactions lack haptic feedback | F54: No haptic/vibration feedback on button presses or important actions despite vibration package being available. | G54: Less tactile experience, reduced user engagement, accessibility issue for users who rely on haptic feedback. | H54: *Add HapticFeedback.lightImpact() on button presses | I54: Mobile UX Best Practices, Accessibility | J54: 45971
A55: UIUX-MP-027 | B55: LOW | C55: Visual - Component Styling | D55: Inconsistent Border Radius Values | E55: Throughout application - mix of 8, 12, 16, 24 border radius values | F55: Border radius values vary inconsistently across the app without a clear design system. | G55: Inconsistent visual design, lack of design cohesion, difficult to maintain consistent look. | H55: *Define standard border radius values in design system | I55: Material Design Shape System | J55: 45971
A56: UIUX-MP-028 | B56: LOW | C56: Bug - Performance | D56: No Code Splitting or Lazy Loading | E56: All imports are eager loaded in main.dart | F56: All screens and features are imported eagerly, increasing initial bundle size and load time. | G56: Slower app startup, larger initial download, unnecessary code loaded. | H56: *Implement lazy loading for non-critical screens | I56: Flutter Performance Optimization | J56: 45971
A57: UIUX-MP-029 | B57: LOW | C57: UI/UX - General Experience | D57: No Pull-to-Refresh Functionality | E57: Lists throughout application lack pull-to-refresh | F57: Trip lists, transaction lists, and other data lists don't have pull-to-refresh capability. | G57: Users cannot easily refresh data. Must navigate away and back. Poor mobile UX. | H57: *Add RefreshIndicator to all list views | I57: Material Design Refresh Patterns | J57: 45971
A58: UIUX-MP-030 | B58: LOW | C58: Visual - Color & Theme | D58: No Dark Mode Support | E58: Theme only defines light theme in mobile-passenger\lib\main.dart:121 | F58: Application only supports light theme, no dark mode implementation despite being common in modern apps. | G58: Poor experience in low-light conditions. Increased battery drain on OLED devices. Not following OS theme preferences. | H58: *Design dark theme color scheme | I58: Material Design Dark Theme, Accessibility | J58: 45971
... A60: UIUX-MP-032 | B60: LOW | C60: Bug - Security & Privacy | D60: No Onboarding Completion Tracking | E60: *mobile-passenger\lib\data\local\cache_helper.dart (onBoardingSkip key exists) | F60: Onboarding can only be skipped, no completion tracking. Users might see onboarding repeatedly. | G60: Annoying user experience if onboarding shows unexpectedly. Unclear onboarding state. | H60: *Add onBoardingCompleted key separate from skip | I60: Onboarding UX Best Practices | J60: 45971
A61: UIUX-MP-033 | B61: LOW | C61: Visual/Color & Theme | D61: Brand colors incorrect | E61: *mobile-passenger/lib/shared/constants/colors_constant.dart | F61: App uses different green than brand guidelines | G61: Brand inconsistency across platforms | H61: Align styling with the JTNY brand palette, verify contrast ratios, and sync shared theme tokens. | I61: JTNY Brand System | J61: 45971 | L61: 7
A62: UIUX-MP-034 | B62: LOW | C62: Visual/Styling | D62: Blurry icons on high DPI | E62: *mobile-passenger/lib/shared/constants/images.dart | F62: Low resolution assets on retina displays | G62: Poor visual quality on premium devices | H62: Normalize the component styling per the design system and run a UX review of the updated elements. | I62: Material Design Visual Guidelines | J62: 45971 | L62: 7
A63: UIUX-MP-035 | B63: LOW | C63: UI/Responsiveness | D63: Rating stars too close | E63: *mobile-passenger/lib/shared/widgets/smooth_star_rating.dart | F63: Driver rating stars overlap on small screens | G63: Difficult to select intended rating | H63: Apply responsive layout updates, verify on target breakpoints, and add visual regression coverage. | I63: Responsive Web Design Best Practices | J63: 45971 | L63: 7
A64: UIUX-MP-036 | B64: LOW | C64: Visual/Consistency | D64: Animation speeds vary | E64: *mobile-passenger/lib/modules/home_page/screens/home_screen.dart | F64: Different animation durations for similar actions | G64: Inconsistent feel | H64: Normalize the component styling per the design system and run a UX review of the updated elements. | I64: Material Design Visual Guidelines | J64: 45971 | L64: 7
A65: UIUX-MP-037 | B65: LOW | C65: UI/Layout Issue | D65: Receipt layout broken | E65: *mobile-passenger/lib/modules/trip_details_screen/screens/trip_details_screen.dart | F65: PDF receipt text overlaps | G65: Receipts look unprofessional | H65: Refactor the layout per the design system, ensure adaptive breakpoints, and validate with QA/Design. | I65: JTNY Admin Layout Guidelines | J65: 45971 | L65: 7
A66: UIUX-MD-001 | B66: CRITICAL | C66: UI/Responsiveness | D66: Map controls overlap trip info | E66: *mobile-driver/lib/modules/trip/providers/map_provider.dart | F66: Google Maps zoom controls cover trip destination on narrow screens | G66: Drivers cannot see destination address during navigation | H66: Apply responsive layout updates, verify on target breakpoints, and add visual regression coverage. | I66: Responsive Web Design Best Practices | J66: 45971 | L66: 5
A67: UIUX-MD-002 | B67: HIGH | C67: Bug - Monitoring & Observability | D67: Advertisement carousel never reaches last slide & leaks timer | E67: *lib/modules/advertisement/widgets/advertisement_widget.dart:22-43 | F67: The auto-play logic stops when `currentIndex <= 3` even though five slides are rendered, and the anonymous `Timer.periodic` is never stored or cancelled in `dispose`. | G67: The final banner is never auto-played and the timer keeps waking the CPU after the widget is removed, causing subtle jank and resource waste. | H67: Refactor the layout per the design system, ensure adaptive breakpoints, and validate with QA/Design. | I67: Material Design – Carousel Patterns; Flutter Timer Lifecycle Guidance | J67: 45971
A68: UIUX-MD-003 | B68: HIGH | C68: UI/UX - General Experience | D68: Trip type displays placeholder text | E68: *lib/modules/home/widgets/single_trip_data.dart:492-505 | F68: The trip type label falls back to the literal string `'noo'` whenever the trip isn't scheduled, leaving a TODO in production UI. | G68: Drivers see gibberish instead of "Standard/Saver/etc.", reducing trust in fare breakdowns and breaking localization. | H68: *Map every known `service` code to a localized label and provide a proper "Unknown" fallback instead of hard-coded placeholder strings. | I68: Material Design – Writing Style; Unicode CLDR Localization Guidelines | J68: 45971
A69: UIUX-MD-004 | B69: HIGH | C69: Bug - State Management | D69: Face ID/Touch ID toggle never appears | E69: *lib/modules/settings/screens/settings_screen.dart:35-58 | F69: `_biometricType` is set asynchronously in `init()` without calling `setState`, but the Face ID switch is guarded by `_biometricType != ''`. | G69: Even on supported devices the biometric login option stays hidden, so drivers cannot enable faster/safer authentication. | H69: *Wrap the `_biometricType` mutation in `setState`, or expose the detection result via a FutureBuilder/Provider before rendering the toggle. | I69: Apple HIG – Face ID Enrollment; Material Security Patterns | J69: 45971
A70: UIUX-MD-005 | B70: HIGH | C70: Bug - State Management | D70: Connectivity detection disabled everywhere | E70: *lib/main.dart:60-67 | F70: The `ConnectivityProvider` is neither registered nor initialized because the provider wiring and `initialize()` call are commented out. | G70: When the network drops, users just see endless loading indicators with no snackbar/dialog, leading to failed trip actions and extra support load. | H70: *Re-enable the provider, call `initialize()` in `didChangeDependencies`, and surface the existing offline snackbar/dialog UX from `ConnectivityProvider`. | I70: Material Design – Connectivity States; WCAG 2.1 Status Messages | J70: 45971
A71: UIUX-MD-006 | B71: HIGH | C71: Bug - API Integration | D71: Trip request timer overflows progress indicator | E71: *lib/modules/home/widgets/request_waiting_time_widget.dart:27-50 | F71: The widget divides elapsed seconds by `requestTime - 5` without clamping and even falls back to a literal `15` when `tripInfo` is null, so `LinearProgressIndicator` is frequently given a value > 1.0. | G71: In debug/test builds this triggers an assertion and in release it pegs the bar instantly, leaving drivers with no visual cue about how long they have left to accept. | H71: *Clamp the ratio between 0 and 1, guard against `requestTime <= 5`, and remove the hard-coded `15` fallback in favor of the indeterminate progress style. | I71: Material Design – Progress Indicators; Flutter ProgressIndicator API Contract | J71: 45971
A72: UIUX-MD-007 | B72: HIGH | C72: Bug - Validation | D72: No validation on OCR-scanned trip kilometer values | E72: *lib/modules/trip/widgets/ocr_widget.dart:166-170 | F72: The OCR widget allows submitting any integer parsed from text without validating if it's reasonable (e.g., negative numbers, zero, or impossibly high values like 999999). | G72: Drivers can accidentally submit incorrect odometer readings due to OCR misreads, leading to incorrect billing, trip calculation errors, and disputes. Malicious drivers could manipulate readings to inflate earnings or avoid tolls based on distance. | H72: *Add validation: minimum value (e.g., > 0), maximum value (e.g., < 10000 for reasonable daily driving), and range checking against previous trip readings if available. | I72: Form Validation Best Practices; Data Integrity Standards | J72: 45971
A73: UIUX-MD-008 | B73: HIGH | C73: Bug - Performance | D73: Image cache never cleared during profile updates | E73: *lib/shared/provider/users_provider.dart:406-408 | F73: When updating profile images, the code clears Flutter's image cache but Firebase Storage caches images with the same URL, causing drivers to see stale profile pictures until app restart. | G73: Drivers upload new profile photos but continue seeing old photos in the app, leading to confusion and multiple re-upload attempts. This wastes bandwidth and storage, and creates poor UX. Support receives complaints about "profile picture not updating". | H73: *Append timestamp or version query parameter to Firebase Storage URLs when fetching updated images: `url?v=${DateTime.now().millisecondsSinceEpoch}`. | I73: Flutter Image Caching Best Practices; HTTP Cache-Control Headers | J73: 45971
A74: UIUX-MD-009 | B74: HIGH | C74: Bug - State Management | D74: No loading state when switching wallet tabs | E74: *lib/modules/wallet/screens/wallet_screen.dart:110-150 | F74: Switching between "Received Money" and "Amount Due" tabs has instant UI change but transactions may not be loaded yet, showing empty lists without indication of loading status. | G74: Users may think they have no transactions when switching tabs, especially on slow connections. This creates confusion and unnecessary support contacts asking "where are my payments?". | H74: *Add loading indicators when tab data is being fetched. | I74: Material Design Progress Indicators; Skeleton Screen Pattern | J74: 45972
A75: UIUX-MD-010 | B75: HIGH | C75: Bug - API Integration | D75: Trip request dialog shows accept button only | E75: *lib/modules/home/widgets/trip_request_dialog.dart:210-226 | F75: The reject button is commented out (lines 210-226), leaving drivers with no way to decline trip requests through UI. They must wait for timeout, which is poor UX. | G75: Drivers cannot reject unwanted trips (long distances, difficult areas, low ratings), forced to let them timeout and potentially receiving penalties for low acceptance rates. This violates driver autonomy and creates frustration. Platform may show decreased driver availability due to artificial timeout delays. | H75: *Uncomment and enable the reject button. | I75: Driver Autonomy Principles; Fair Labor Standards; UX Best Practices | J75: 45972
A76: UIUX-MD-011 | B76: HIGH | C76: Bug - Performance | D76: No pagination or virtual scrolling in trip history | E76: *lib/modules/home/screens/all_trips_screen.dart | F76: While pagination is implemented on backend calls (page count), the UI loads all trips into memory at once without virtual scrolling. Drivers with hundreds of trips experience lag and memory issues. | G76: For drivers with 500+ completed trips, the app becomes sluggish, experiences frame drops, and may crash with OutOfMemoryError on older devices. ListView builds all widgets at once instead of lazily building visible items only. | H76: *Implement ListView.builder with lazy loading instead of generating all widgets upfront. | I76: Flutter Performance Best Practices; Lazy Loading Patterns; Material Design Scrolling Patterns | J76: 45972
A77: UIUX-MD-012 | B77: HIGH | C77: Bug - Error Handling | D77: No feedback when biometric authentication fails to initialize | E77: *lib/modules/settings/screens/settings_screen.dart:35-58 | F77: `init()` method calls `LocalAuth.getBiometrics()` but never shows error message to user if biometric detection fails. User just sees the toggle never appear without explanation. | G77: Drivers on devices with biometric hardware issues or disabled biometrics see no toggle and no explanation, leading to confusion. They may think the feature is unavailable on their device model when it's actually a configuration or hardware issue. | H77: *Wrap biometric initialization in try-catch and show snackbar or dialog if it fails: "Biometric authentication unavailable. Please check your device settings." | I77: Material Design Error Handling; Accessibility Error Messaging; WCAG 2.1 Error Identification | J77: 45972
A78: UIUX-MD-013 | B78: HIGH | C78: Bug - API Integration | D78: No offline mode indicators or queuing | E78: App-wide (no connectivity provider registered) | F78: While `ConnectivityProvider` exists, it's commented out in main.dart:66 and never initialized. App has no way to detect offline state, queue failed operations, or inform user about connectivity issues beyond API timeout errors. | G78: Users on poor networks experience unexplained failures, API timeouts showing generic errors, and lost data when operations fail during connectivity loss. No way to queue trip status updates, location updates, or messages for later sync. This creates data inconsistencies and user frustration. | H78: *Uncomment and properly initialize ConnectivityProvider. | I78: Offline-First Architecture Patterns; Material Design Connectivity States; Progressive Enhancement | J78: 45972
... A81: UIUX-MD-016 | B81: HIGH | C81: Bug - State Management | D81: No confirmation dialog when changing payment method | E81: *lib/modules/trip/providers/trip_provider.dart:58-61 | F81: The `changePaymentWay` function switches between cash/card payment without showing a confirmation dialog, allowing accidental taps to change payment method mid-trip. | G81: Drivers accidentally tap the payment method toggle during trips, changing from card to cash without realizing it. At trip end, payment collection fails, leading to disputes with passengers, revenue loss, and accounting errors. Drivers don't get paid for completed trips. | H81: *Add confirmation dialog before changing payment method: "Switch to [cash/card]? This action cannot be undone." Disable payment method switching after passenger boarding. | I81: Financial Transaction Safety Patterns; Confirmation Dialog Best Practices; Audit Trail Requirements | J81: 45972
A82: UIUX-MD-017 | B82: HIGH | C82: UI/Layout Issue | D82: Trip request modal cuts off on small screens | E82: *mobile-driver/lib/modules/home/widgets/trip_request_dialog.dart | F82: Trip request popup modal bottom buttons not visible on phones < 5.5 inches | G82: Drivers cannot accept trips on 40% of Android devices | H82: Refactor the layout per the design system, ensure adaptive breakpoints, and validate with QA/Design. | I82: JTNY Admin Layout Guidelines | J82: 45972 | L82: 5
A83: UIUX-MD-018 | B83: HIGH | C83: UI/Navigation | D83: Back button exits app unexpectedly | E83: *mobile-driver/lib/modules/home/screens/main_screen.dart | F83: Android back button exits app instead of going back one screen | G83: Drivers accidentally close app losing trip state | H83: Provide clear navigation controls, persist state, and add UX/integration tests for the flow. | I83: Jakob Nielsen Navigation Heuristics | J83: 45972 | L83: 5
A84: UIUX-MD-019 | B84: HIGH | C84: Visual/Color & Theme | D84: Status colors unclear | E84: *mobile-driver/lib/shared/utils/app_colors.dart | F84: Online/offline status uses similar shades of green | G84: Drivers unsure of their availability status | H84: Align styling with the JTNY brand palette, verify contrast ratios, and sync shared theme tokens. | I84: JTNY Brand System | J84: 45972 | L84: 5
A85: UIUX-MD-020 | B85: HIGH | C85: UI/Responsiveness | D85: Chat keyboard covers input | E85: *mobile-driver/lib/modules/driver_passenger_chat/messages_widgets/submitting_message_textfield.dart | F85: Keyboard hides message input field in chat | G85: Cannot see what they're typing to passengers | H85: Apply responsive layout updates, verify on target breakpoints, and add visual regression coverage. | I85: Responsive Web Design Best Practices | J85: 45972 | L85: 5
A86: UIUX-MD-021 | B86: HIGH | C86: UI/Accessibility | D86: No voice navigation | E86: *mobile-driver/lib/modules/trip/providers/map_provider.dart | F86: Turn-by-turn directions not announced | G86: Dangerous as drivers must look at screen | H86: Provide clear navigation controls, persist state, and add UX/integration tests for the flow. | I86: WCAG 2.1 Level AA | J86: 45972 | L86: 5
A87: UIUX-MD-022 | B87: HIGH | C87: UI/Navigation | D87: Can't return from trip details | E87: *mobile-driver/lib/modules/trip/screens/trip_details_screen.dart | F87: No back button in trip history details | G87: Stuck in screen requiring app restart | H87: Provide clear navigation controls, persist state, and add UX/integration tests for the flow. | I87: Jakob Nielsen Navigation Heuristics | J87: 45972 | L87: 5
A88: UIUX-MD-023 | B88: MEDIUM | C88: Bug - State Management | D88: Missing empty states in wallet and trip history screens | E88: *lib/modules/wallet/screens/wallet_screen.dart:152-181 | F88: When drivers have no transactions or trips, screens show empty ListView without explanation, helpful message, or call-to-action, making it unclear if data failed to load or actually empty. | G88: New drivers see blank screens and think the app is broken, leading to unnecessary support contacts. Experienced drivers between payouts think transaction data failed to load. Poor onboarding experience discourages new driver engagement. | H88: *Add empty state widgets with illustrations and helpful text: "No trips yet" with "Go online to start earning!" CTA for trip screen, "No transactions yet" for wallet. | I88: Material Design Empty States; Onboarding Best Practices; User Engagement Patterns | J88: 45972
A89: UIUX-MD-024 | B89: MEDIUM | C89: Bug - API Integration | D89: No visual indication of trip request timeout countdown | E89: *lib/modules/home/widgets/request_waiting_time_widget.dart:27-50 | F89: The `LinearProgressIndicator` shows progress but there's no numeric countdown timer (e.g., "15s remaining") to give drivers clear feedback on urgency. | G89: Drivers don't know exactly how much time they have left to decide on accepting a trip request. The progress bar can be misinterpreted or missed, leading to missed opportunities or rushed decisions without proper evaluation of trip details. | H89: *Add a text widget showing countdown: "Accept within ${remainingSeconds}s". | I89: Time-Sensitive UI Patterns; Material Design Progress Indicators; Accessible Countdown Timers | J89: 45972
A90: UIUX-MD-025 | B90: MEDIUM | C90: UI/Accessibility | D90: Text too small for driving | E90: *mobile-driver/lib/modules/trip/widgets/trip_information_widget.dart | F90: Trip details text at 12px unreadable while driving | G90: Safety hazard as drivers squint to read information | H90: Apply WCAG-compliant changes (aria labels, focus order, contrast) and verify with assistive tech. | I90: WCAG 2.1 Level AA | J90: 45972 | L90: 7
A91: UIUX-MD-026 | B91: MEDIUM | C91: Visual/Styling | D91: Inconsistent iOS/Android UI | E91: *mobile-driver/lib/config/theme/app_theme.dart | F91: Different UI elements and layouts between platforms | G91: Confusion when drivers switch devices | H91: Refactor the layout per the design system, ensure adaptive breakpoints, and validate with QA/Design. | I91: Material Design Visual Guidelines | J91: 45972 | L91: 7
A92: UIUX-MD-027 | B92: MEDIUM | C92: UI/Layout Issue | D92: Earnings chart unreadable | E92: *mobile-driver/lib/modules/wallet/screens/wallet_screen.dart | F92: Daily earnings chart labels overlap on 7-day view | G92: Drivers cannot track earnings properly | H92: Refactor the layout per the design system, ensure adaptive breakpoints, and validate with QA/Design. | I92: JTNY Admin Layout Guidelines | J92: 45972 | L92: 7
A93: UIUX-MD-028 | B93: MEDIUM | C93: UI/Navigation | D93: Confusing tab navigation | E93: *mobile-driver/lib/modules/home/screens/main_screen.dart | F93: Bottom tabs don't highlight current section | G93: Drivers unsure which section they're in | H93: Provide clear navigation controls, persist state, and add UX/integration tests for the flow. | I93: Jakob Nielsen Navigation Heuristics | J93: 45972 | L93: 7
A94: UIUX-MD-029 | B94: MEDIUM | C94: Visual/Consistency | D94: Icon size variations | E94: *mobile-driver/lib/shared/widgets/custom_button.dart | F94: Icons range from 16px to 32px randomly | G94: Visual imbalance and unprofessional look | H94: Normalize the component styling per the design system and run a UX review of the updated elements. | I94: Material Design Visual Guidelines | J94: 45972 | L94: 7
A95: UIUX-MD-030 | B95: MEDIUM | C95: UI/Responsiveness | D95: Landscape mode broken | E95: *mobile-driver/lib/modules/home/screens/map_screen.dart | F95: UI doesn't adapt to landscape orientation | G95: Cannot use app in landscape car mounts | H95: Apply responsive layout updates, verify on target breakpoints, and add visual regression coverage. | I95: Responsive Web Design Best Practices | J95: 45972 | L95: 7
A96: UIUX-MD-031 | B96: MEDIUM | C96: Visual/Color & Theme | D96: Night mode missing | E96: *mobile-driver/lib/config/theme/app_theme.dart | F96: Bright white background at night | G96: Eye strain during night driving | H96: Align styling with the JTNY brand palette, verify contrast ratios, and sync shared theme tokens. | I96: JTNY Brand System | J96: 45972 | L96: 7
A97: UIUX-MD-032 | B97: MEDIUM | C97: UI/Accessibility | D97: Small touch targets | E97: *mobile-driver/lib/shared/widgets/custom_button.dart | F97: Buttons smaller than 44x44px minimum | G97: Difficult to tap while driving | H97: Apply WCAG-compliant changes (aria labels, focus order, contrast) and verify with assistive tech. | I97: WCAG 2.1 Level AA | J97: 45972 | L97: 7
A98: UIUX-MD-033 | B98: MEDIUM | C98: UI/Layout Issue | D98: Overlapping elements in RTL | E98: *mobile-driver/lib/modules/home/screens/main_screen.dart | F98: Arabic layout has overlapping text | G98: Arabic interface partially unusable | H98: Refactor the layout per the design system, ensure adaptive breakpoints, and validate with QA/Design. | I98: JTNY Admin Layout Guidelines | J98: 45972 | L98: 7
A99: UIUX-MD-034 | B99: LOW | C99: Bug - Performance | D99: Unused imports and dependencies bloat APK size | E99: *pubspec.yaml` | F99: Several commented-out dependencies remain in pubspec.yaml (device_info_plus, connectivity_plus, internet_connection_checker_plus, open_settings, sign_in_with_apple) and unused imports exist throughout the codebase, increasing build times and APK size. | G99: Larger APK size (likely 5-10MB overhead) leads to fewer downloads in markets with data caps or slow connections, longer install times, more storage consumption on user devices, and increased build/compile times for developers. | H99: Normalize the component styling per the design system and run a UX review of the updated elements. | I99: Flutter APK Size Optimization; Mobile App Performance Best Practices | J99: 45972
A100: UIUX-MD-035 | B100: LOW | C100: Visual/Consistency | D100: Multiple button styles | E100: *mobile-driver/lib/shared/widgets/custom_button.dart | F100: Five different button designs throughout app | G100: Unprofessional appearance | H100: Normalize the component styling per the design system and run a UX review of the updated elements. | I100: Material Design Visual Guidelines | J100: 45972 | L100: 7
A101: UIUX-MD-036 | B101: LOW | C101: Visual/Styling | D101: Outdated Material Design | E101: *mobile-driver/lib/config/theme/app_theme.dart | F101: Using Material Design 1.0 components | G101: App looks dated compared to competitors | H101: Normalize the component styling per the design system and run a UX review of the updated elements. | I101: Material Design Visual Guidelines | J101: 45972 | L101: 7
A102: UIUX-MD-037 | B102: LOW | C102: UI/Layout Issue | D102: Profile image distorted | E102: *mobile-driver/lib/modules/profile/widgets/custom_profile_image_widget.dart | F102: Square images stretched in circular frame | G102: Unprofessional profile appearance | H102: Refactor the layout per the design system, ensure adaptive breakpoints, and validate with QA/Design. | I102: JTNY Admin Layout Guidelines | J102: 45972 | L102: 7
A103: UIUX-MD-038 | B103: LOW | C103: Visual/Consistency | D103: Font inconsistency | E103: *mobile-driver/lib/config/theme/app_theme.dart | F103: Mix of system and custom fonts | G103: Unprofessional appearance | H103: Normalize the component styling per the design system and run a UX review of the updated elements. | I103: Material Design Visual Guidelines | J103: 45972 | L103: 7
...

Sheet Bugs&CodeQuality_Analysis
A1: SEITech | M1: JTNY | Q1: SEITech
A2: ID | B2: Severity | C2: Category | D2: Issue | E2: Location | F2: Description | G2: Impact | H2: Actions Required | I2: Standards/Guidelines Followed | J2: Log Date | K2: Estimation (WD) | L2: Milestone | M2: Investigation Result / Team Reply | N2: Status | O2: Responsible | P2: Date of Reply | Q2: Feedback | R2: Date of Reply | S2: Customer Feedback
A3: BUGS-SA-001 | B3: CRITICAL | C3: Bug - Build & Tooling | D3: Missing Dependencies in Package.json | E3: *sharapp\package.json | F3: Application cannot run without npm install. All dependencies are marked as UNMET. | G3: Production blocker for SharApp because Application cannot run without npm install. All dependencies are marked as UNMET. As a result, deployments fail and engineers lose hours on remediation. | H3: *Run npm install to install all dependencies. This is a deployment/setup issue that will prevent the application from working. | I3: The Twelve-Factor App - Dependencies; npm Package Management Best Practices | J3: 45970 | L3: 3
A4: BUGS-SA-002 | B4: CRITICAL | C4: Bug - Error Handling | D4: Unsafe Type Assertion with Non-null Assertion Operator | E4: *sharapp\src\main.tsx (Line 6) | F4: Application will crash if the root element doesn't exist. No fallback or error handling. | G4: Production blocker for SharApp because Application will crash if the root element doesn't exist. No fallback or error handling. As a result, users lose confidence. | H4: *Add null check and error handling before rendering. | I4: TypeScript Handbook - Strict Null Checks; React DOM Rendering Guidelines | J4: 45970 | L4: 3
A5: BUGS-SA-003 | B5: CRITICAL | C5: Bug - Error Handling | D5: Unhandled Promise Rejection in Geocoder | E5: *sharapp\src\useGeocoder.ts (Lines 18-20) | F5: If geocoding fails, the error is silently ignored. Users won't see current location information. | G5: Production blocker for SharApp because If geocoding fails, the error is silently ignored. Users won't see current location information. As a result, users lose confidence. | H5: *Add .catch() handler to manage geocoding failures gracefully. | I5: OWASP ASVS v4.0 V8 Error Handling and Logging; TC39 Promise Rejection Handling | J5: 45970 | L5: 3
A6: BUGS-SA-004 | B6: CRITICAL | C6: Visual - Icons & Imagery | D6: Missing Image Path Leading Slash | E6: *sharapp\src\TripInformation.tsx (Line 103) | F6: Image will fail to load for standard JTNY class cars. | G6: Production blocker for SharApp because Image will fail to load for standard JTNY class cars. As a result, visual cues become misleading. | H6: *Add leading slash to make path absolute. | I6: W3C HTML Living Standard - Resource Loading; React Static Asset Guidelines | J6: 45970 | L6: 3
A7: BUGS-SA-005 | B7: CRITICAL | C7: Bug - Code Quality | D7: Weak Comparison Operators | E7: *sharapp\src\utils.ts (Lines 77-78) | F7: Type coercion could lead to unexpected behavior. Not following TypeScript/JavaScript best practices. | G7: Production blocker for SharApp because Type coercion could lead to unexpected behavior. Not following TypeScript/JavaScript best practices. As a result, users lose confidence. | H7: *Use strict equality (===) instead of loose equality (==). | I7: ESLint eqeqeq rule | J7: 45970 | L7: 3
A8: BUGS-SA-006 | B8: HIGH | C8: Bug - Error Handling | D8: No Error Boundary Implementation | E8: *All component files | F8: If any component crashes, the entire app will white screen with no user-friendly error message. | G8: Major disruption for SharApp because If any component crashes, the entire app will white screen with no user-friendly error message. As a result, users lose confidence. | H8: *Implement Error Boundary component to catch and handle React errors gracefully. | I8: React Best Practices | J8: 45970 | L8: 4
A9: BUGS-SA-007 | B9: HIGH | C9: Bug - API Integration | D9: Incomplete Error Handling in API Calls | E9: *sharapp\src\tripApi.ts (Lines 16-27, 38-56) | F9: Network errors, 404s, 500s, and other HTTP errors are not explicitly handled. Users see generic error page without specific information. | G9: Major disruption for SharApp because Network errors, 404s, 500s, and other HTTP errors are not explicitly handled. Users see generic error page without specific information. As a result, client requests fail unpredictably. | H9: *Add response status checks and throw descriptive errors. Handle different error scenarios (network failure, unauthorized, server error, etc.). | I9: OWASP ASVS v4.0 V5 API Error Handling; REST API Design Guidelines | J9: 45970 | L9: 4
A10: BUGS-SA-008 | B10: HIGH | C10: Bug - Code Quality | D10: Hardcoded Currency Symbol | E10: *sharapp\src\TripInformation.tsx (Line 154) | F10: Currency is hardcoded as "L.E" (Egyptian Pound) but data structure includes currency_symbol_en. Inconsistent display. | G10: Major disruption for SharApp because Currency is hardcoded as "L.E" (Egyptian Pound) but data structure includes currency_symbol_en. Inconsistent display. As a result, users lose confidence. | H10: *Use tripInformation.country.currency_symbol_en for consistency. | I10: ISO 4217 Currency Codes; W3C Internationalization Best Practices | J10: 45970 | L10: 4
A11: BUGS-SA-009 | B11: HIGH | C11: Bug - API Integration | D11: Map Crashes When Destination Coordinates Are Missing | E11: *sharapp/src/TripSharingMap.tsx:30-33 | F11: When the API returns an empty destinations_locations array (common before a passenger sets the drop-off), tripInformation.destinations_locations[0] is undefined and the component throws while reading .lat/.long, blanking the entire map panel. | G11: Major disruption for SharApp because When the API returns an empty destinations_locations array (common before a passenger sets the drop-off), tripInformation.destinations_locations[0] is undefined and the component throws while reading .lat/.long, blanking the entire map panel. As a result, client requests fail unpredictably. | H11: *Guard for empty arrays, show a placeholder like “Destination pending,” and skip fitBounds until the first set of coordinates arrives. | I11: Google Maps Platform Data Validation Guidelines; Defensive Programming Practices | J11: 45970 | L11: 4
A12: BUGS-SA-010 | B12: MEDIUM | C12: Bug - Security & Privacy | D12: Weak Key Generation in Lists | E12: *sharapp\src\TripSharingMap.tsx (Line 58) | F12: Keys based on coordinates or names may not be unique if duplicates exist. React reconciliation may fail. Using destination name as key is not guaranteed to be unique. | G12: Noticeable degradation for SharApp because Keys based on coordinates or names may not be unique if duplicates exist. React reconciliation may fail. Using destination name as key is not guaranteed to be unique. As a result, sensitive data and trust are at immediate risk. | H12: *Use unique IDs from API or index with prefix (e.g., key={dest-${index}}). | I12: React Documentation - Lists and Keys; Airbnb React/JSX Style Guide | J12: 45970 | L12: 6
A13: BUGS-SA-011 | B13: MEDIUM | C13: Bug - Build & Tooling | D13: Missing TypeScript Strict Mode Enforcement | E13: *sharapp\tsconfig.json | F13: While "strict" is true, some type safety issues exist (non-null assertions, any types implied). | G13: Noticeable degradation for SharApp because While "strict" is true, some type safety issues exist (non-null assertions, any types implied). As a result, deployments fail and engineers lose hours on remediation. | H13: *Enable additional strict checks and fix resulting type errors. | I13: TypeScript Compiler strict Mode; Microsoft Secure Coding Guidelines | J13: 45970 | L13: 6
A14: BUGS-SA-012 | B14: MEDIUM | C14: Bug - Security & Privacy | D14: React Query Cache Not Parameterized by Trip Inputs | E14: *sharapp/src/useTripURLInformation.ts:11-22 | F14: The query key is always ["tripInformation"], so opening another share link in the same tab (different server/tripId/tripType/token) keeps showing stale data from the previous cache entry and never re-fetches until a hard reload. Tokens also can’t be rotated without a manual invalidation. | G14: Noticeable degradation for SharApp because The query key is always ["tripInformation"], so opening another share link in the same tab (different server/tripId/tripType/token) keeps showing stale data from the previous cache entry and never re-fetches until a hard reload. Tokens also can’t be rotated without a manual invalidation. As a result, sensitive data and trust are at immediate risk. | H14: *Include server, tripType, tripId, and token in the query key (e.g., ["tripInformation", server, tripType, tripId, token]) and add an enabled guard so React Query automatically rehydrates whenever the URL changes. | I14: TanStack Query Cache Key Guidelines; REST API Caching Best Practices | J14: 45970 | L14: 6
... A112: BUGS-DF-029 | B112: LOW | C112: Compliance | D112: No Account Deletion Option | E112: No visible account deletion or data retention policy | F112: Users cannot delete their accounts. No data retention timeframes visible. Required by GDPR right to erasure. | G112: GDPR Article 17 violation. Cannot fulfill deletion requests. Indefinite data retention. Legal risk. | H112: *Add account deletion feature. *Implement data retention policies. *Soft delete with recovery period. *Document retention periods. | I112: GDPR Article 17 - Right to Erasure | J112: 45972 | L112: 6
A113: BUGS-DB-001 | B113: CRITICAL | C113: Bug - Security & Privacy | D113: Firebase Private Key Exposed | E113: `api\green-cadb3-firebase.json` Lines 1-14 | F113: Complete Firebase service account private key exposed in version control including: - private_key (RSA private key) - private_key_id - client_email - client_id | G113: Full Firebase database access. Attackers can read/write/delete all Firebase data, impersonate service account, access Google Cloud resources. Data breach, data manipulation, service disruption. | H113: 1. IMMEDIATELY revoke the service account 2. Create new service account with minimal permissions 3. Remove JSON file from repository 4. Store in secure vault (Azure Key Vault, AWS Secrets Manager) 5. Audit all Firebase data for unauthorized access | I113: OWASP A02:2021 - Cryptographic Failures; CWE-522: Insufficiently Protected Credentials; GDPR Article 32 | J113: 45972
A114: BUGS-DB-002 | B114: CRITICAL | C114: Bug - API Integration | D114: DEBUG Mode Enabled in Dev | E114: `api\settings\dev.py` Line 4 | F114: DEBUG = True in development settings, risk of being used in production | G114: Information disclosure, detailed error pages exposing system internals, performance impact | H114: 1. Ensure DEBUG=False in production 2. Use environment-specific settings 3. Add deployment checks 4. Implement proper error pages 5. Add DEBUG detection in startup | I114: OWASP A05:2021 - Security Misconfiguration; Django Security Best Practices | J114: 45972
A115: BUGS-DB-003 | B115: HIGH | C115: Bug - Security & Privacy | D115: Weak Password Policy | E115: `Account\serializers.py` Lines 218, 292, 544, 642 | F115: Password minimum length only 6 characters with no complexity requirements (no uppercase, special chars, numbers required) | G115: Weak passwords vulnerable to brute force attacks, dictionary attacks, credential stuffing | H115: 1. Increase minimum password length to 12 characters 2. Require complexity (uppercase, lowercase, numbers, special chars) 3. Implement password strength meter 4. Check against common password lists 5. Enforce password history | I115: OWASP A07:2021 - Identification and Authentication Failures; NIST 800-63B Password Guidelines; CWE-521: Weak Password Requirements | J115: 45972
A116: BUGS-DB-004 | B116: HIGH | C116: Bug - Security & Privacy | D116: OTP Token Expiry Too Long | E116: `Account\models.py` Line 82 | F116: OTP tokens valid for 420 seconds (7 minutes). Standard is 60-90 seconds | G116: Extended attack window for OTP brute force, increases risk of OTP interception/replay | H116: 1. Reduce OTP validity to 60-90 seconds 2. Implement OTP attempt limiting (max 3-5 attempts) 3. Add OTP throttling 4. Invalidate OTP after successful use 5. Log failed OTP attempts | I116: OWASP A07:2021 - Identification and Authentication Failures; NIST 800-63B OTP Guidelines | J116: 45972
A117: BUGS-DB-005 | B117: HIGH | C117: Bug - Security & Privacy | D117: Insufficient Session Management | E117: `Account\authentications.py` Lines 20-46 | F117: Custom authentication doesn't implement session fixation protection, concurrent session limits, or session binding | G117: Session hijacking, session fixation, concurrent session abuse, unauthorized access | H117: 1. Implement session fixation protection 2. Add concurrent session limits 3. Bind sessions to IP/User-Agent 4. Implement session timeout 5. Add logout from all devices functionality | I117: OWASP A07:2021 - Identification and Authentication Failures; CWE-384: Session Fixation | J117: 45972
A118: BUGS-DB-006 | B118: HIGH | C118: Bug - Security & Privacy | D118: Missing CSRF Token Validation | E118: `api\settings\base.py` Line 120 | F118: CSRF middleware enabled but no enforcement on state-changing operations. Multiple AllowAny endpoints bypass CSRF | G118: Cross-Site Request Forgery attacks, unauthorized state changes, data manipulation | H118: 1. Ensure CSRF tokens on all state-changing operations 2. Remove BasicAuthentication which bypasses CSRF 3. Implement SameSite cookie attribute 4. Add CSRF_TRUSTED_ORIGINS 5. Enable CSRF_COOKIE_SECURE | I118: OWASP A01:2021 - Broken Access Control; CWE-352: Cross-Site Request Forgery | J118: 45972
A119: BUGS-DB-007 | B119: HIGH | C119: Bug - Monitoring & Observability | D119: No Account Lockout Mechanism | E119: `Account\views.py` Lines 126-270 | F119: No account lockout after failed login attempts. Unlimited authentication attempts allowed | G119: Brute force attacks, credential stuffing, password spraying attacks | H119: 1. Implement account lockout after 5-10 failed attempts 2. Add progressive delays between attempts 3. Implement CAPTCHA after failed attempts 4. Add account unlock mechanism 5. Send security alerts on lockout | I119: OWASP A07:2021 - Identification and Authentication Failures; CWE-307: Improper Restriction of Excessive Authentication Attempts | J119: 45972
A120: BUGS-DB-008 | B120: HIGH | C120: Bug - Security & Privacy | D120: PyJWT Version Vulnerability | E120: `requirements.txt` Line 57 | F120: PyJWT 2.5.0 may have vulnerabilities. Latest stable is 2.8+ | G120: JWT token vulnerabilities, authentication bypass potential | H120: 1. Upgrade PyJWT to latest version 2. Review JWT implementation 3. Test token validation 4. Implement token security best practices | I120: OWASP A06:2021 - Vulnerable and Outdated Components | J120: 45972
A121: BUGS-DB-009 | B121: MEDIUM | C121: Bug - Compliance & Regulatory | D121: Missing Audit Logging for Sensitive Operations | E121: Throughout codebase | F121: Insufficient audit logging for authentication events, authorization failures, data access, configuration changes | G121: Cannot detect security incidents, comply with regulations, forensic analysis impossible | H121: 1. Implement comprehensive audit logging 2. Log all authentication events 3. Log authorization failures 4. Log sensitive data access 5. Implement log monitoring and alerting 6. Ensure logs are tamper-proof | I121: OWASP A09:2021 - Security Logging and Monitoring Failures; GDPR Article 30; PCI DSS 10.1 | J121: 45972
A122: BUGS-DB-010 | B122: MEDIUM | C122: Bug - API Integration | D122: Missing Request Size Limits | E122: *dashboard-backend/api/settings/base.py:60-140 | F122: No request size limits configured | G122: DoS attacks via large payloads, memory exhaustion, resource abuse | H122: 1. Set DATA_UPLOAD_MAX_MEMORY_SIZE 2. Set FILE_UPLOAD_MAX_MEMORY_SIZE 3. Implement request body size limits 4. Add file upload validation 5. Monitor large requests | I122: OWASP A04:2021 - Insecure Design; CWE-770: Allocation of Resources Without Limits | J122: 45972
A123: BUGS-DB-011 | B123: MEDIUM | C123: Bug - State Management | D123: Commented Out Code | E123: Throughout codebase (e.g., `Account\views.py` Lines 98-125, 639-696, 699-786) | F123: Large blocks of commented code reducing readability and maintenance | G123: Code bloat, confusion, maintenance burden, potential security issues if uncommented accidentally | H123: 1. Remove all commented code 2. Use version control for history 3. Document decisions in commit messages 4. Clean up codebase 5. Implement code review process | I123: Clean Code Principles; SOLID Principles | J123: 45972
A124: BUGS-DB-012 | B124: MEDIUM | C124: Bug - Error Handling | D124: Excessive Exception Handling with Print | E124: Multiple files (e.g., `Transaction\views.py` Line 114 `Car\views.py` Lines 155, 169, 425) | F124: Exceptions caught but only printed, not properly logged or handled | G124: Silent failures, debugging difficulties, production issues undetected | H124: 1. Replace print() with proper logging 2. Implement exception monitoring (Sentry) 3. Add proper error handling 4. Set up alerting 5. Log with context information | I124: Python Logging Best Practices; 12-Factor App | J124: 45972
... A135: BUGS-MB-008 | B135: MEDIUM | C135: Bug - General Code Quality | D135: clean_drivers_data Zips Unrelated Firestore Collections | E135: mobile-backend/Modules/firebase.py:31-44 | F135: clean_drivers_data zips the driver and driver_trip collections, assuming equal ordering and length, then updates each pair. | G135: Whenever the collection sizes diverge, drivers receive another driver's status/trip info, corrupting live availability data. | H135: Iterate driver collections independently by document ID, handle missing trip documents gracefully, and add tests for asymmetry. | I135: ISO/IEC 25010 Reliability | J135: 45972

Sheet AWS_Audit
A1: SEITech | N1: JTNY | R1: SEITech
A2: ID | B2: Severity | C2: Category | D2: Issue | E2: Location | F2: Description | G2: Impact | H2: Actions Required | I2: Standards/Guidelines Followed | J2: Savings/month | K2: Log Date | L2: Estimation (WD) | M2: Milestone | N2: Investigation Result / Team Reply | O2: Status | P2: Responsible | Q2: Date of Reply | R2: Feedback | S2: Date of Reply | T2: Customer Feedback
A3: AWS-001 | B3: CRITICAL | C3: Architecture | D3: The EC2 instance i-01d9d8b30a74fae1b (mobile) is over provisioned. | E3: EC2-Dashboard | F3: According to CPU usage and AWS recommendations, this EC2 is over provisioned and needs reduced compute capacity. | G3: High spend on idle compute; AWS projects 70% cost savings if rightsized. | H3: Change EC2 type from m5dn.2xlarge to is4gen.medium. | I3: AWS Well-Architected Framework – Cost Optimization Pillar AWS Compute Optimizer Rightsizing Guidance | J3: 327.492 | K3: 45971 | M3: 2
A4: AWS-002 | B4: CRITICAL | C4: Architecture | D4: The EC2 instance i-0eb1bbd45ea19979e (live2) is over provisioned. | E4: EC2-Dashboard | F4: Based on CPU metrics and AWS guidance, this EC2 is oversized for the workload. | G4: Paying 42% more than necessary for unused capacity. | H4: Change EC2 type from m5dn.large to c6gd.large. | I4: AWS Well-Architected Framework – Cost Optimization Pillar AWS Compute Optimizer Rightsizing Guidance | J4: 47.304 | K4: 45941 | M4: 2
A5: AWS-003 | B5: CRITICAL | C5: Architecture | D5: The EC2 instance i-0e935890cfd61f7c0 (live) is mis-sized. | E5: EC2-Dashboard | F5: Usage data shows the instance can be downsized without impacting performance. | G5: Approximately 15% of compute spend can be saved while meeting capacity needs. | H5: Change EC2 type from m5dn.xlarge to r6gd.xlarge. | I5: AWS Well-Architected Framework – Cost Optimization Pillar AWS Compute Optimizer Recommendations | J5: 35.02 | K5: 45972 | M5: 2
A6: AWS-004 | B6: CRITICAL | C6: Architecture | D6: The EC2 instance i-0520151b34ebc5ef6 (staging-mobile) is over provisioned. | E6: EC2-Dashboard | F6: CPU utilization trends indicate the current size is excessive for staging traffic. | G6: Spending 57% more than required for the staging environment. | H6: Change EC2 type from m5n.large to r6g.medium. | I6: AWS Well-Architected Framework – Cost Optimization Pillar AWS Compute Optimizer Rightsizing Guidance | J6: 55.918 | K6: 45972 | M6: 2
A7: AWS-005 | B7: CRITICAL | C7: Architecture | D7: The EC2 instance i-076e8ec11457150f6 (live2-front-staging) is over provisioned. | E7: EC2-Dashboard | F7: Monitoring shows the instance is mostly idle for its allocated size. | G7: Excess compute spend with up to 88% reduction available. | H7: Change EC2 type from c6a.xlarge to t4g.small. | I7: AWS Well-Architected Framework – Cost Optimization Pillar AWS Compute Optimizer Rightsizing Guidance | J7: 106.404 | K7: 45972 | M7: 2
A8: AWS-006 | B8: CRITICAL | C8: Architecture | D8: The EC2 instance i-0d1ebd56f4b6b206c (recover-test) is over provisioned. | E8: EC2-Dashboard | F8: Usage telemetry confirms the DR/test node is rightsizeable. | G8: Overpaying by ~55% for the recovery test environment. | H8: Change EC2 type from m5n.2xlarge to r6g.xlarge. | I8: AWS Well-Architected Framework – Cost Optimization Pillar AWS Compute Optimizer Recommendations | J8: 223.671 | K8: 45972 | M8: 2
A9: AWS-007 | B9: CRITICAL | C9: Architecture | D9: Over provisioned EC2 resources make up ~71.4% of October 2025 cost. | E9: EC2-Dashboard | F9: Most EC2 machines (6 of 7) are oversized, driving the majority of spend. | G9: Sustained high infrastructure cost because compute dominates the bill. | H9: Apply the rightsizing actions described in AWS-001 through AWS-007. | I9: AWS Well-Architected Framework – Cost Optimization Pillar; FinOps Foundation Rightsizing Playbook | K9: 45972 | M9: 2
A10: AWS-008 | B10: CRITICAL | C10: Architecture - Storage | D10: Too many EBS volume snapshots are retained, including very old copies. | E10: EC2-Dashboard | F10: Snapshot inventory has grown without lifecycle management. | G10: Over-consumption of persistent storage and risk of restoring outdated data. | H10: Define and enforce a backup strategy with retention limits per project requirements. | I10: AWS Well-Architected Framework – Reliability Pillar; AWS Backup Best Practices Whitepaper | K10: 45972 | M10: 2
A11: AWS-009 | B11: CRITICAL | C11: Architecture - Storage | D11: No consistent time slot is defined between backups. | E11: EC2-Dashboard | F11: Snapshots occur irregularly, leaving unclear recovery points. | G11: Potential data-loss window due to inconsistent RPO/RTO expectations. | H11: Define backup cadence, time slots, and incremental policies aligned to requirements. | I11: AWS Well-Architected Framework – Reliability Pillar; AWS Backup Best Practices Whitepaper | K11: 45972 | M11: 2
A12: AWS-010 | B12: CRITICAL | C12: Archi-SG | D12: Security risk: port 22 (SSH) is open to the world on most EC2 instances. | E12: EC2-Dashboard | F12: Security groups allow 0.0.0.0/0 to port 22. | G12: High likelihood of brute-force or credential-stuffing attacks. | H12: Restrict SSH to trusted IP ranges or VPN jump hosts; close public access. | I12: AWS Well-Architected Framework – Reliability Pillar; AWS Backup Best Practices Whitepaper | K12: 45972 | M12: 2
A13: AWS-011 | B13: CRITICAL | C13: Archi-SG | D13: Database port is exposed to the internet (0.0.0.0/0) for EC2 i-0e935890cfd61f7c0. | E13: EC2-Dashboard | F13: DB listener accepts public traffic, violating least-privilege networking. | G13: Risk of unauthorized access, data exfiltration, or SQL exploits. | H13: Close or restrict the database port to trusted networks/private subnets. | I13: AWS Well-Architected Framework – Reliability Pillar; AWS Backup Best Practices Whitepaper | K13: 45972 | M13: 2
A14: AWS-012 | B14: HIGH | C14: AWS-Feature | D14: AWS Cost Optimization Hub is disabled. | E14: Dashboard | F14: The feature that surfaces automated savings opportunities is not active. | G14: Limited visibility into AWS-native cost KPIs and actions. | H14: Enable Cost Optimization Hub in the payer account. | I14: AWS Well-Architected Framework – Cost Optimization Pillar; AWS Billing & Cost Management Best Practices | K14: 45972 | M14: 2
A15: AWS-013 | B15: HIGH | C15: Archi-SG | D15: HTTP port 80 is open, allowing unencrypted public access. | E15: EC2-Dashboard | F15: Traffic is accepted over plaintext HTTP without redirects. | G15: Exposure to interception, downgrade, and session hijacking attacks. | H15: Redirect HTTP to HTTPS (443) or close port 80 entirely. | I15: AWS Well-Architected Framework – Security Pillar; OWASP ASVS 2.1.1 Transport Layer Requirements | K15: 45972 | M15: 2
A16: AWS-014 | B16: HIGH | C16: Architecture | D16: Low and inconsistent network activity indicates over-provisioned capacity. | E16: EC2-Dashboard | F16: Network In/Out metrics stay minimal with only occasional spikes. | G16: Paying for unused bandwidth and higher-tier networking features. | H16: Review workload transfer needs and right-size or shift to cheaper networking tiers. | I16: AWS Well-Architected Framework – Cost Optimization & Performance Efficiency Pillars; AWS Compute Optimizer | K16: 45972 | M16: 2
A17: AWS-015 | B17: HIGH | C17: Architecture | D17: CPU utilization stays mostly under 10%. | E17: EC2-Dashboard | F17: Instance is oversized relative to compute demand. | G17: Wasting budget on idle vCPUs and power overhead. | H17: Downsize to a smaller EC2 type or enable Auto Scaling to match workload. | I17: AWS Well-Architected Framework – Cost Optimization Pillar; FinOps Rightsizing Best Practices | K17: 45972 | M17: 2
A18: AWS-016 | B18: HIGH | C18: Architecture | D18: Memory usage averages below 10%. | E18: EC2-Dashboard | F18: RAM headroom is far beyond what the service uses. | G18: Higher cost without corresponding performance benefit. | H18: Move to an instance family with less RAM or consolidate workloads. | I18: AWS Well-Architected Framework – Cost Optimization & Performance Efficiency Pillars | M18: 2
A19: AWS-017 | B19: HIGH | C19: Architecture | D19: Very low read/write operations suggest over-provisioned storage. | E19: EC2-Dashboard | F19: Disk I/O metrics are nearly flat with rare spikes. | G19: Paying for premium IOPS/volume size not being used. | H19: Reduce EBS size or switch to gp3/lower-tier storage to cut cost. | I19: AWS Well-Architected Framework – Cost Optimization Pillar; AWS EBS Volume Performance Guidelines | M19: 2
A20: AWS-018 | B20: HIGH | C20: Architecture | D20: “Over-provisioned” status across all key metrics. | E20: EC2-Dashboard | F20: AWS recommendations indicate resources (CPU, memory, network, disk) are larger than workload needs. | G20: Increased monthly costs, inefficient resource management, and missed cost optimization opportunities. | H20: Implement Cost Optimization Hub findings, apply rightsizing recommendations, and automate scaling based on actual usage patterns | I20: AWS Well-Architected Framework – Cost Optimization & Performance Efficiency Pillars | M20: 2
A21: AWS-019 | B21: CRITICAL | C21: Security/Logging | D21: CloudTrail management events disabled | F21: 22 regions/accounts lack CloudTrail management event logging & validation. | G21: Control-plane changes go unrecorded; audit/compliance violations and limited forensic capability | H21: Enable multi-region CloudTrail with log validation, KMS encryption, and SNS notifications; store logs in immutable S3. | I21: AWS CIS 3.1, ISO 27001 A.12.4, NIST 800-53 AU-2 | M21: 2
A22: AWS-020 | B22: CRITICAL | C22: Identity & Access | D22: External resource sharing via IAM Access Analyzer findings | F22: 22 IAM Access Analyzer alerts indicate resources shared with external principals. | G22: Unintended cross-account access can expose data or infrastructure controls. | H22: Review each analyzer finding, restrict resource policies, or document approved external access | I22: AWS CIS 1.20, Principle of Least Privilege | M22: 2
A23: AWS-021 | B23: MEDIUM | C23: Backup & DR | D23: Unmanaged EBS/RDS snapshot lifecycle | E23: AWS-Console | F23: Snapshots retained indefinitely with inconsistent intervals; no defined RPO/RTO | G23: Storage cost bloat and potential data loss if recent recovery points missing. | H23: Define backup policy, implement Lifecycle Manager/Automated snapshots, purge obsolete snapshots. | I23: AWS Reliability Pillar, ISO 27001 A.12.3 | M23: 2
A24: AWS-022 | B24: HIGH | C24: Identity & Access | D24: MFA and key rotation gaps in IAM users | E24: AWS-Console | F24: Console users (audit-user, muhab) lack MFA; SES SMTP users use static keys without rotation; root account password active. | G24: Credential compromise can lead to full account takeover or SES abuse. | H24: Enforce MFA for all console users, rotate/disable legacy access keys, restrict root to break-glass only. | I24: AWS CIS 1.1/1.5, NIST IA-2, ISO 27001 A.9 | M24: 2
A25: AWS-023 | B25: LOW | C25: Cost Optimization | D25: Unassociated Elastic IP addresses | E25: AWS-Console | F25: Two Elastic IPs remain allocated without attachments in eu-west-1. | G25: Creates recurring hourly charges and increases the chance of unexpected reuse of stale IPs. | H25: Release unused addresses or associate them with active resources; implement cleanup automation. | I25: AWS Cost Optimization Best Practices | M25: 2
A26: AWS-024 | B26: MEDIUM | C26: Storage Optimization | D26: Underutilized Amazon EBS volumes | E26: AWS-Console | F26: Two gp2 volumes show consistently low throughput yet reserve high provisioned capacity. | G26: Paying for unused provisioned performance and risking missed lifecycle policies. | H26: Resize or snapshot-and-delete dormant volumes; migrate to gp3 with lower baseline cost. | I26: AWS Well-Architected Cost Optimization Pillar, Storage Lifecycle Guidance | M26: 2
A27: AWS-025 | B27: MEDIUM | C27: Cost Optimization | D27: Missing Savings Plan / RI coverage | E27: AWS-Console | F27: Trusted Advisor highlights insufficient Savings Plan commitments relative to steady EC2 usage. | G27: On-demand pricing leaves 15?20% savings unrealized across baseline compute. | H27: Purchase 1-year no-upfront Compute Savings Plans sized to baseline usage and monitor coverage monthly. | I27: AWS Cost Optimization Pillar, FinOps Commitment Management | M27: 2
A28: AWS-026 | B28: MEDIUM | C28: Network Security | D28: Application Load Balancers serving HTTP health checks | E28: AWS-Console | F28: Two ALB target groups keep HTTP-only listeners and health checks, sending plaintext traffic inside VPC. | G28: Prevents enforcing TLS end-to-end and exposes credentials/headers during health checks. | H28: Switch ALB listeners and health checks to HTTPS, require TLS certificates, and limit listener ports. | I28: AWS Well-Architected Security Pillar, TLS Best Practices | M28: 2
A29: AWS-027 | B29: MEDIUM | C29: Cost Optimization | D29: Reserved Instance optimization warnings | E29: AWS-Console | F29: Trusted Advisor shows six RI mismatch/opportunity alerts indicating underutilized reservations or missing coverage. | G29: Continued on-demand usage and RI wastage reduces effective discount rate. | H29: Rebalance or modify existing RIs and align purchases with current instance families and regions. | I29: AWS Cost Optimization Pillar, FinOps Commitment Management | M29: 2
A30: AWS-028 | B30: HIGH | C30: Network Security | D30: Security Groups – Unrestricted Access | E30: AWS-Console | F30: 4 of 14 security group rules allow unrestricted access (0.0.0.0/0) to specific ports. | G30: Increases the attack surface by allowing anyone on the internet to reach application ports, risking brute-force and exploitation attacks. | H30: Restrict inbound rules to specific IP ranges or VPC CIDRs; implement Network ACLs or AWS WAF for extra protection. | M30: 2
A31: AWS-029 | B31: HIGH | C31: Network / Load Balancing | D31: Application Load Balancer Security Group Misconfiguration | E31: AWS-Console | F31: 1 of 2 ALB security groups allow overly permissive access or improper configuration. | G31: Potential exposure of backend EC2 instances to the public or bypass of security controls. | H31: Harden the ALB security group by allowing only required inbound traffic from trusted IPs or AWS-managed services. | I31: AWS Well-Architected Security Pillar | M31: 2
